Workbook
Name Alíquota: #REF!
Name Alíquota: 'Alíquotas ICMS'!$O$5:$O$13
Name UF: #REF!
Name UF: 'Tabela mensal ICMS'!$B$35:$B$63

Sheet Orientações
C2: Instruções de preenchimento da planilha de apuração
B4: 1. | C4: Preencher o ano fiscal na célula C1 da aba "Apuração";
B5: 2. | C5: Preencher as tabelas "(A) Receita" e "(B) Cancelamentos e descontos incondicionais" na aba "Apuração" com os dados contábeis da ROB-telecom (preferencialmente abertos por UF);
B6: 3. | C6: Identificar as contas de interconexão (ITX) ou EILD na coluna "D" da aba "apuração";
B7: 4.a | C7: Para ano fiscal 2022 e posteriores, selecionar a UF de cada linha de receita na coluna "E" (usando a lista suspensa);
C8: [para receitas sem identificação da UF, selecionar "n/d" | para receitas sem reconhecimento contábil de ICMS, selecionar "NT" (não tributado)]
B9: 4.b | C9: Para ano fiscal até 2021, selecionar a alíquota geral de ICMS em cada linha de receita na coluna "E" (usando a lista suspensa);
C10: [para receitas sem reconhecimento contábil de ICMS, selecionar "0%"]
B11: 5. | C11: Aba "ICMS", independentemente do ano fiscal, adequar manualmente a indicação das alíquotas mensais de cada linha de receita nas colunas "T" a "AE";
C12: [considerar resposta da prestadora, convênios de ICMS, adicional de FECP, diferenciais de alíquota por serviços específicos, etc.]
B13: 6. | C13: Aba "ICMS", preencher a tabela "ICMS contabilizado" (linhas 28 a 30) com os dados contábeis da despesa de ICMS (redutora de receita de telecom);
B14: 7. | C14: Aba "ICMS", identificar as eventuais contas contábeis de ICMS referentes a interconexão (ITX) ou EILD na coluna "D";
B15: 8. | C15: Aba "Apuração", conferir se o total de PIS e Cofins (células R29 e R30) não excedem os respectivos saldos contábeis equivalentes às receitas de telecom;
B16: 9. | C16: Copiar os valores da tabela "Resumo para upload" na aba "Apuração" para o arquivo modelo gerador do CSV.
B17: 10. | C17: Copiar as tabelas resumo para a conclusão do relatório de fiscalização no SEI.

Sheet Resumo
B2: ="Tabela 1 - Totais apurados - "&Apuração!$C$1 -> Tabela 1 - Totais apurados - 2022
B3: Mês | C3: ROB Telecom (Total) | D3: (-) ICMS | E3: (-) PIS | F3: (-) COFINS | G3: Fust 1% | H3: Funttel 0,5%
B4: Janeiro | C4: =Apuração!$F$45 -> 0 | D4: =Apuração!$F$46 -> 0 | E4: =Apuração!$F$47 -> 0 | F4: =Apuração!$F$48 -> 0 | G4: =TRUNC(SUM(C4,-D4,-E4,-F4)*1%,2) -> 0 | H4: =TRUNC(SUM(C4,-D4,-E4,-F4)*0.5%,2) -> 0
B5: Fevereiro | C5: =Apuração!$G$45 -> 0 | D5: =Apuração!$G$46 -> 0 | E5: =Apuração!$G$47 -> 0 | F5: =Apuração!$G$48 -> 0 | G5: =TRUNC(SUM(C5,-D5,-E5,-F5)*1%,2) -> 0 | H5: =TRUNC(SUM(C5,-D5,-E5,-F5)*0.5%,2) -> 0
B6: Março | C6: =Apuração!$H$45 -> 0 | D6: =Apuração!$H$46 -> 0 | E6: =Apuração!$H$47 -> 0 | F6: =Apuração!$H$48 -> 0 | G6: =TRUNC(SUM(C6,-D6,-E6,-F6)*1%,2) -> 0 | H6: =TRUNC(SUM(C6,-D6,-E6,-F6)*0.5%,2) -> 0
B7: Abril | C7: =Apuração!$I$45 -> 0 | D7: =Apuração!$I$46 -> 0 | E7: =Apuração!$I$47 -> 0 | F7: =Apuração!$I$48 -> 0 | G7: =TRUNC(SUM(C7,-D7,-E7,-F7)*1%,2) -> 0 | H7: =TRUNC(SUM(C7,-D7,-E7,-F7)*0.5%,2) -> 0
B8: Maio | C8: =Apuração!$J$45 -> 0 | D8: =Apuração!$J$46 -> 0 | E8: =Apuração!$J$47 -> 0 | F8: =Apuração!$J$48 -> 0 | G8: =TRUNC(SUM(C8,-D8,-E8,-F8)*1%,2) -> 0 | H8: =TRUNC(SUM(C8,-D8,-E8,-F8)*0.5%,2) -> 0
B9: Junho | C9: =Apuração!$K$45 -> 0 | D9: =Apuração!$K$46 -> 0 | E9: =Apuração!$K$47 -> 0 | F9: =Apuração!$K$48 -> 0 | G9: =TRUNC(SUM(C9,-D9,-E9,-F9)*1%,2) -> 0 | H9: =TRUNC(SUM(C9,-D9,-E9,-F9)*0.5%,2) -> 0
B10: Julho | C10: =Apuração!$L$45 -> 0 | D10: =Apuração!$L$46 -> 0 | E10: =Apuração!$L$47 -> 0 | F10: =Apuração!$L$48 -> 0 | G10: =TRUNC(SUM(C10,-D10,-E10,-F10)*1%,2) -> 0 | H10: =TRUNC(SUM(C10,-D10,-E10,-F10)*0.5%,2) -> 0
B11: Agosto | C11: =Apuração!$M$45 -> 0 | D11: =Apuração!$M$46 -> 0 | E11: =Apuração!$M$47 -> 0 | F11: =Apuração!$M$48 -> 0 | G11: =TRUNC(SUM(C11,-D11,-E11,-F11)*1%,2) -> 0 | H11: =TRUNC(SUM(C11,-D11,-E11,-F11)*0.5%,2) -> 0
B12: Setembro | C12: =Apuração!$N$45 -> 0 | D12: =Apuração!$N$46 -> 0 | E12: =Apuração!$N$47 -> 0 | F12: =Apuração!$N$48 -> 0 | G12: =TRUNC(SUM(C12,-D12,-E12,-F12)*1%,2) -> 0 | H12: =TRUNC(SUM(C12,-D12,-E12,-F12)*0.5%,2) -> 0
B13: Outubro | C13: =Apuração!$O$45 -> 0 | D13: =Apuração!$O$46 -> 0 | E13: =Apuração!$O$47 -> 0 | F13: =Apuração!$O$48 -> 0 | G13: =TRUNC(SUM(C13,-D13,-E13,-F13)*1%,2) -> 0 | H13: =TRUNC(SUM(C13,-D13,-E13,-F13)*0.5%,2) -> 0
B14: Novembro | C14: =Apuração!$P$45 -> 0 | D14: =Apuração!$P$46 -> 0 | E14: =Apuração!$P$47 -> 0 | F14: =Apuração!$P$48 -> 0 | G14: =TRUNC(SUM(C14,-D14,-E14,-F14)*1%,2) -> 0 | H14: =TRUNC(SUM(C14,-D14,-E14,-F14)*0.5%,2) -> 0
B15: Dezembro | C15: =Apuração!$Q$45 -> 0 | D15: =Apuração!$Q$46 -> 0 | E15: =Apuração!$Q$47 -> 0 | F15: =Apuração!$Q$48 -> 0 | G15: =TRUNC(SUM(C15,-D15,-E15,-F15)*1%,2) -> 0 | H15: =TRUNC(SUM(C15,-D15,-E15,-F15)*0.5%,2) -> 0
B16: Total Anual | C16: =SUM(C4:C15) -> 0 | D16: =SUM(D4:D15) -> 0 | E16: =SUM(E4:E15) -> 0 | F16: =SUM(F4:F15) -> 0 | G16: =SUM(G4:G15) -> 0 | H16: =SUM(H4:H15) -> 0
B19: Tabela 2 - Apuração somente Interconexão (ITX) e EILD
B20: Mês | C20: ROB Telecom (ITX/EILD) | D20: (-) ICMS | E20: (-) PIS | F20: (-) COFINS | G20: Fust 1% | H20: Funttel 0,5%
B21: Janeiro | C21: =Apuração!$F$51 -> 0 | D21: =Apuração!$F$52 -> 0 | E21: =Apuração!$F$53 -> 0 | F21: =Apuração!$F$54 -> 0 | G21: =TRUNC(SUM(C21,-D21,-E21,-F21)*1%,2) -> 0 | H21: =TRUNC(SUM(C21,-D21,-E21,-F21)*0.5%,2) -> 0
B22: Fevereiro | C22: =Apuração!$G$51 -> 0 | D22: =Apuração!$G$52 -> 0 | E22: =Apuração!$G$53 -> 0 | F22: =Apuração!$G$54 -> 0 | G22: =TRUNC(SUM(C22,-D22,-E22,-F22)*1%,2) -> 0 | H22: =TRUNC(SUM(C22,-D22,-E22,-F22)*0.5%,2) -> 0
B23: Março | C23: =Apuração!$H$51 -> 0 | D23: =Apuração!$H$52 -> 0 | E23: =Apuração!$H$53 -> 0 | F23: =Apuração!$H$54 -> 0 | G23: =TRUNC(SUM(C23,-D23,-E23,-F23)*1%,2) -> 0 | H23: =TRUNC(SUM(C23,-D23,-E23,-F23)*0.5%,2) -> 0
B24: Abril | C24: =Apuração!$I$51 -> 0 | D24: =Apuração!$I$52 -> 0 | E24: =Apuração!$I$53 -> 0 | F24: =Apuração!$I$54 -> 0 | G24: =TRUNC(SUM(C24,-D24,-E24,-F24)*1%,2) -> 0 | H24: =TRUNC(SUM(C24,-D24,-E24,-F24)*0.5%,2) -> 0
B25: Maio | C25: =Apuração!$J$51 -> 0 | D25: =Apuração!$J$52 -> 0 | E25: =Apuração!$J$53 -> 0 | F25: =Apuração!$J$54 -> 0 | G25: =TRUNC(SUM(C25,-D25,-E25,-F25)*1%,2) -> 0 | H25: =TRUNC(SUM(C25,-D25,-E25,-F25)*0.5%,2) -> 0
B26: Junho | C26: =Apuração!$K$51 -> 0 | D26: =Apuração!$K$52 -> 0 | E26: =Apuração!$K$53 -> 0 | F26: =Apuração!$K$54 -> 0 | G26: =TRUNC(SUM(C26,-D26,-E26,-F26)*1%,2) -> 0 | H26: =TRUNC(SUM(C26,-D26,-E26,-F26)*0.5%,2) -> 0
B27: Julho | C27: =Apuração!$L$51 -> 0 | D27: =Apuração!$L$52 -> 0 | E27: =Apuração!$L$53 -> 0 | F27: =Apuração!$L$54 -> 0 | G27: =TRUNC(SUM(C27,-D27,-E27,-F27)*1%,2) -> 0 | H27: =TRUNC(SUM(C27,-D27,-E27,-F27)*0.5%,2) -> 0
B28: Agosto | C28: =Apuração!$M$51 -> 0 | D28: =Apuração!$M$52 -> 0 | E28: =Apuração!$M$53 -> 0 | F28: =Apuração!$M$54 -> 0 | G28: =TRUNC(SUM(C28,-D28,-E28,-F28)*1%,2) -> 0 | H28: =TRUNC(SUM(C28,-D28,-E28,-F28)*0.5%,2) -> 0
B29: Setembro | C29: =Apuração!$N$51 -> 0 | D29: =Apuração!$N$52 -> 0 | E29: =Apuração!$N$53 -> 0 | F29: =Apuração!$N$54 -> 0 | G29: =TRUNC(SUM(C29,-D29,-E29,-F29)*1%,2) -> 0 | H29: =TRUNC(SUM(C29,-D29,-E29,-F29)*0.5%,2) -> 0
B30: Outubro | C30: =Apuração!$O$51 -> 0 | D30: =Apuração!$O$52 -> 0 | E30: =Apuração!$O$53 -> 0 | F30: =Apuração!$O$54 -> 0 | G30: =TRUNC(SUM(C30,-D30,-E30,-F30)*1%,2) -> 0 | H30: =TRUNC(SUM(C30,-D30,-E30,-F30)*0.5%,2) -> 0
B31: Novembro | C31: =Apuração!$P$51 -> 0 | D31: =Apuração!$P$52 -> 0 | E31: =Apuração!$P$53 -> 0 | F31: =Apuração!$P$54 -> 0 | G31: =TRUNC(SUM(C31,-D31,-E31,-F31)*1%,2) -> 0 | H31: =TRUNC(SUM(C31,-D31,-E31,-F31)*0.5%,2) -> 0
B32: Dezembro | C32: =Apuração!$Q$51 -> 0 | D32: =Apuração!$Q$52 -> 0 | E32: =Apuração!$Q$53 -> 0 | F32: =Apuração!$Q$54 -> 0 | G32: =TRUNC(SUM(C32,-D32,-E32,-F32)*1%,2) -> 0 | H32: =TRUNC(SUM(C32,-D32,-E32,-F32)*0.5%,2) -> 0
B33: Total Anual | C33: =SUM(C21:C32) -> 0 | D33: =SUM(D21:D32) -> 0 | E33: =SUM(E21:E32) -> 0 | F33: =SUM(F21:F32) -> 0 | G33: =SUM(G21:G32) -> 0 | H33: =SUM(H21:H32) -> 0
B36: Tabela 3 - Apuração sem Interconexão (ITX) e EILD Tabela 1 (-) Tabela 2
B37: Mês | C37: ROB Telecom (demais) | D37: (-) ICMS | E37: (-) PIS | F37: (-) COFINS | G37: Fust 1% | H37: Funttel 0,5%
B38: Janeiro | C38: =C4-C21 -> 0 | D38: =D4-D21 -> 0 | E38: =E4-E21 -> 0 | F38: =F4-F21 -> 0 | G38: =G4-G21 -> 0 | H38: =H4-H21 -> 0
B39: Fevereiro | C39: =C5-C22 -> 0 | D39: =D5-D22 -> 0 | E39: =E5-E22 -> 0 | F39: =F5-F22 -> 0 | G39: =G5-G22 -> 0 | H39: =H5-H22 -> 0
B40: Março | C40: =C6-C23 -> 0 | D40: =D6-D23 -> 0 | E40: =E6-E23 -> 0 | F40: =F6-F23 -> 0 | G40: =G6-G23 -> 0 | H40: =H6-H23 -> 0
B41: Abril | C41: =C7-C24 -> 0 | D41: =D7-D24 -> 0 | E41: =E7-E24 -> 0 | F41: =F7-F24 -> 0 | G41: =G7-G24 -> 0 | H41: =H7-H24 -> 0
B42: Maio | C42: =C8-C25 -> 0 | D42: =D8-D25 -> 0 | E42: =E8-E25 -> 0 | F42: =F8-F25 -> 0 | G42: =G8-G25 -> 0 | H42: =H8-H25 -> 0
B43: Junho | C43: =C9-C26 -> 0 | D43: =D9-D26 -> 0 | E43: =E9-E26 -> 0 | F43: =F9-F26 -> 0 | G43: =G9-G26 -> 0 | H43: =H9-H26 -> 0
B44: Julho | C44: =C10-C27 -> 0 | D44: =D10-D27 -> 0 | E44: =E10-E27 -> 0 | F44: =F10-F27 -> 0 | G44: =G10-G27 -> 0 | H44: =H10-H27 -> 0
B45: Agosto | C45: =C11-C28 -> 0 | D45: =D11-D28 -> 0 | E45: =E11-E28 -> 0 | F45: =F11-F28 -> 0 | G45: =G11-G28 -> 0 | H45: =H11-H28 -> 0
B46: Setembro | C46: =C12-C29 -> 0 | D46: =D12-D29 -> 0 | E46: =E12-E29 -> 0 | F46: =F12-F29 -> 0 | G46: =G12-G29 -> 0 | H46: =H12-H29 -> 0
B47: Outubro | C47: =C13-C30 -> 0 | D47: =D13-D30 -> 0 | E47: =E13-E30 -> 0 | F47: =F13-F30 -> 0 | G47: =G13-G30 -> 0 | H47: =H13-H30 -> 0
B48: Novembro | C48: =C14-C31 -> 0 | D48: =D14-D31 -> 0 | E48: =E14-E31 -> 0 | F48: =F14-F31 -> 0 | G48: =G14-G31 -> 0 | H48: =H14-H31 -> 0
B49: Dezembro | C49: =C15-C32 -> 0 | D49: =D15-D32 -> 0 | E49: =E15-E32 -> 0 | F49: =F15-F32 -> 0 | G49: =G15-G32 -> 0 | H49: =H15-H32 -> 0
B50: Total Anual | C50: =SUM(C38:C49) -> 0 | D50: =SUM(D38:D49) -> 0 | E50: =SUM(E38:E49) -> 0 | F50: =SUM(F38:F49) -> 0 | G50: =SUM(G38:G49) -> 0 | H50: =SUM(H38:H49) -> 0

Sheet Apuração
B1: Ano fiscal: | C1: 2022 | F1: 1 | G1: 2 | H1: 3 | I1: 4 | J1: 5 | K1: 6 | L1: 7 | M1: 8 | N1: 9 | O1: 10 | P1: 11 | Q1: 12
B2: ="CÁLCULO DO FUST/FUNTTEL - ANO "&C1 -> CÁLCULO DO FUST/FUNTTEL - ANO 2022 | D2: ITX / | E2: ICMS | F2: RECEITAS | R2: TOTAL ANUAL
B3: CODIGO | C3: CONTA | D3: EILD? | E3: =IF(C1>=2022,"UF","Alíquota") -> UF | F3: =DATE(RIGHT($B$2,4),F1,1) -> 44562 | G3: =DATE(RIGHT($B$2,4),G1,1) -> 44593 | H3: =DATE(RIGHT($B$2,4),H1,1) -> 44621 | I3: =DATE(RIGHT($B$2,4),I1,1) -> 44652 | J3: =DATE(RIGHT($B$2,4),J1,1) -> 44682 | K3: =DATE(RIGHT($B$2,4),K1,1) -> 44713 | L3: =DATE(RIGHT($B$2,4),L1,1) -> 44743 | M3: =DATE(RIGHT($B$2,4),M1,1) -> 44774 | ... Q3: =DATE(RIGHT($B$2,4),Q1,1) -> 44896
B5: (A) Receita
R6: =SUM(F6:Q6) -> 0
R7: =SUM(F7:Q7) -> 0
R8: =SUM(F8:Q8) -> 0
R9: =SUM(F9:Q9) -> 0
R10: =SUM(F10:Q10) -> 0
B11: TOTAL (A) | F11: =SUM(F6:F10) -> 0 | G11: =SUM(G6:G10) -> 0 | H11: =SUM(H6:H10) -> 0 | I11: =SUM(I6:I10) -> 0 | J11: =SUM(J6:J10) -> 0 | K11: =SUM(K6:K10) -> 0 | L11: =SUM(L6:L10) -> 0 | M11: =SUM(M6:M10) -> 0 | ... Q11: =SUM(Q6:Q10) -> 0 | R11: =SUM(F11:Q11) -> 0
B12: (B) Cancelamentos e descontos incondicionais
R13: =SUM(F13:Q13) -> 0
R14: =SUM(F14:Q14) -> 0
R15: =SUM(F15:Q15) -> 0
B16: TOTAL (B) | F16: =SUM(F13:F15) -> 0 | G16: =SUM(G13:G15) -> 0 | H16: =SUM(H13:H15) -> 0 | I16: =SUM(I13:I15) -> 0 | J16: =SUM(J13:J15) -> 0 | K16: =SUM(K13:K15) -> 0 | L16: =SUM(L13:L15) -> 0 | M16: =SUM(M13:M15) -> 0 | ... Q16: =SUM(Q13:Q15) -> 0 | R16: =SUM(F16:Q16) -> 0
C18: (A) + (B) | F18: =F11+F16 -> 0 | G18: =G11+G16 -> 0 | H18: =H11+H16 -> 0 | I18: =I11+I16 -> 0 | J18: =J11+J16 -> 0 | K18: =K11+K16 -> 0 | L18: =L11+L16 -> 0 | M18: =M11+M16 -> 0 | ... Q18: =Q11+Q16 -> 0 | R18: =SUM(F18:Q18) -> 0
B20: EXCLUSÕES LEGAIS | E20: Alíquota
B21: ( - ) | C21: ICMS | E21: - | F21: =ICMS!F26*IF(PRODUCT($R$18,ICMS!$R$26)>0,-1,1) -> 0 | G21: =ICMS!G26*IF(PRODUCT($R$18,ICMS!$R$26)>0,-1,1) -> 0 | H21: =ICMS!H26*IF(PRODUCT($R$18,ICMS!$R$26)>0,-1,1) -> 0 | I21: =ICMS!I26*IF(PRODUCT($R$18,ICMS!$R$26)>0,-1,1) -> 0 | J21: =ICMS!J26*IF(PRODUCT($R$18,ICMS!$R$26)>0,-1,1) -> 0 | K21: =ICMS!K26*IF(PRODUCT($R$18,ICMS!$R$26)>0,-1,1) -> 0 | L21: =ICMS!L26*IF(PRODUCT($R$18,ICMS!$R$26)>0,-1,1) -> 0 | M21: =ICMS!M26*IF(PRODUCT($R$18,ICMS!$R$26)>0,-1,1) -> 0 | ... Q21: =ICMS!Q26*IF(PRODUCT($R$18,ICMS!$R$26)>0,-1,1) -> 0 | R21: =SUM(F21:Q21) -> 0
B22: ( - ) | C22: PIS | E22: 0.0065 | F22: =TRUNC(-(F$18+IF(RIGHT($B$2,4)*1>2017,F$21,0))*$E22,2) -> 0 | G22: =TRUNC(-(G$18+IF(RIGHT($B$2,4)*1>2017,G$21,0))*$E22,2) -> 0 | H22: =TRUNC(-(H$18+IF(RIGHT($B$2,4)*1>2016,H$21,0))*$E22,2) -> 0 | I22: =TRUNC(-(I$18+IF(RIGHT($B$2,4)*1>2016,I$21,0))*$E22,2) -> 0 | J22: =TRUNC(-(J$18+IF(RIGHT($B$2,4)*1>2016,J$21,0))*$E22,2) -> 0 | K22: =TRUNC(-(K$18+IF(RIGHT($B$2,4)*1>2016,K$21,0))*$E22,2) -> 0 | L22: =TRUNC(-(L$18+IF(RIGHT($B$2,4)*1>2016,L$21,0))*$E22,2) -> 0 | M22: =TRUNC(-(M$18+IF(RIGHT($B$2,4)*1>2016,M$21,0))*$E22,2) -> 0 | N22: =TRUNC(-(N$18+IF(RIGHT($B$2,4)*1>2016,N$21,0))*$E22,2) -> 0 | O22: =TRUNC(-(O$18+IF(RIGHT($B$2,4)*1>2016,O$21,0))*$E22,2) -> 0 | ... Q22: =TRUNC(-(Q$18+IF(RIGHT($B$2,4)*1>2016,Q$21,0))*$E22,2) -> 0 | R22: =SUM(F22:Q22) -> 0
B23: ( - ) | C23: COFINS | E23: 0.03 | F23: =TRUNC(-(F$18+IF(RIGHT($B$2,4)*1>2017,F$21,0))*$E23,2) -> 0 | G23: =TRUNC(-(G$18+IF(RIGHT($B$2,4)*1>2017,G$21,0))*$E23,2) -> 0 | H23: =TRUNC(-(H$18+IF(RIGHT($B$2,4)*1>2016,H$21,0))*$E23,2) -> 0 | I23: =TRUNC(-(I$18+IF(RIGHT($B$2,4)*1>2016,I$21,0))*$E23,2) -> 0 | J23: =TRUNC(-(J$18+IF(RIGHT($B$2,4)*1>2016,J$21,0))*$E23,2) -> 0 | K23: =TRUNC(-(K$18+IF(RIGHT($B$2,4)*1>2016,K$21,0))*$E23,2) -> 0 | L23: =TRUNC(-(L$18+IF(RIGHT($B$2,4)*1>2016,L$21,0))*$E23,2) -> 0 | M23: =TRUNC(-(M$18+IF(RIGHT($B$2,4)*1>2016,M$21,0))*$E23,2) -> 0 | N23: =TRUNC(-(N$18+IF(RIGHT($B$2,4)*1>2016,N$21,0))*$E23,2) -> 0 | O23: =TRUNC(-(O$18+IF(RIGHT($B$2,4)*1>2016,O$21,0))*$E23,2) -> 0 | ... Q23: =TRUNC(-(Q$18+IF(RIGHT($B$2,4)*1>2016,Q$21,0))*$E23,2) -> 0 | R23: =SUM(F23:Q23) -> 0
B24: TOTAL | F24: =SUM(F21:F23) -> 0 | G24: =SUM(G21:G23) -> 0 | H24: =SUM(H21:H23) -> 0 | I24: =SUM(I21:I23) -> 0 | J24: =SUM(J21:J23) -> 0 | K24: =SUM(K21:K23) -> 0 | L24: =SUM(L21:L23) -> 0 | M24: =SUM(M21:M23) -> 0 | ... Q24: =SUM(Q21:Q23) -> 0 | R24: =SUM(F24:Q24) -> 0
B25: BASE DE CÁLCULO | F25: =F18+F24 -> 0 | G25: =G18+G24 -> 0 | H25: =H18+H24 -> 0 | I25: =I18+I24 -> 0 | J25: =J18+J24 -> 0 | K25: =K18+K24 -> 0 | L25: =L18+L24 -> 0 | M25: =M18+M24 -> 0 | ... Q25: =Q18+Q24 -> 0 | R25: =SUM(F25:Q25) -> 0
C28: VALORES DEVIDOS
C29: FUST | E29: 0.01 | F29: =-TRUNC(F$25*$E29,2) -> 0 | G29: =-TRUNC(G$25*$E29,2) -> 0 | H29: =-TRUNC(H$25*$E29,2) -> 0 | I29: =-TRUNC(I$25*$E29,2) -> 0 | J29: =-TRUNC(J$25*$E29,2) -> 0 | K29: =-TRUNC(K$25*$E29,2) -> 0 | L29: =-TRUNC(L$25*$E29,2) -> 0 | M29: =-TRUNC(M$25*$E29,2) -> 0 | ... Q29: =-TRUNC(Q$25*$E29,2) -> 0 | R29: =SUM(F29:Q29) -> 0
C30: FUNTTEL | E30: 0.005 | F30: =-TRUNC(F$25*$E30,2) -> 0 | G30: =-TRUNC(G$25*$E30,2) -> 0 | H30: =-TRUNC(H$25*$E30,2) -> 0 | I30: =-TRUNC(I$25*$E30,2) -> 0 | J30: =-TRUNC(J$25*$E30,2) -> 0 | K30: =-TRUNC(K$25*$E30,2) -> 0 | L30: =-TRUNC(L$25*$E30,2) -> 0 | M30: =-TRUNC(M$25*$E30,2) -> 0 | ... Q30: =-TRUNC(Q$25*$E30,2) -> 0 | R30: =SUM(F30:Q30) -> 0
C33: SEGREGAÇÃO INTERCONEXÃO/EILD
C34: Receita | F34: =SUMIFS(F$6:F$15,$D$6:$D$15,"ITX")+SUMIFS(F$6:F$15,$D$6:$D$15,"EILD") -> 0 | G34: =SUMIFS(G$6:G$15,$D$6:$D$15,"ITX")+SUMIFS(G$6:G$15,$D$6:$D$15,"EILD") -> 0 | H34: =SUMIFS(H$6:H$15,$D$6:$D$15,"ITX")+SUMIFS(H$6:H$15,$D$6:$D$15,"EILD") -> 0 | I34: =SUMIFS(I$6:I$15,$D$6:$D$15,"ITX")+SUMIFS(I$6:I$15,$D$6:$D$15,"EILD") -> 0 | J34: =SUMIFS(J$6:J$15,$D$6:$D$15,"ITX")+SUMIFS(J$6:J$15,$D$6:$D$15,"EILD") -> 0 | K34: =SUMIFS(K$6:K$15,$D$6:$D$15,"ITX")+SUMIFS(K$6:K$15,$D$6:$D$15,"EILD") -> 0 | L34: =SUMIFS(L$6:L$15,$D$6:$D$15,"ITX")+SUMIFS(L$6:L$15,$D$6:$D$15,"EILD") -> 0 | M34: =SUMIFS(M$6:M$15,$D$6:$D$15,"ITX")+SUMIFS(M$6:M$15,$D$6:$D$15,"EILD") -> 0 | ... Q34: =SUMIFS(Q$6:Q$15,$D$6:$D$15,"ITX")+SUMIFS(Q$6:Q$15,$D$6:$D$15,"EILD") -> 0 | R34: =SUM(F34:Q34) -> 0
C35: ICMS | F35: =ICMS!F29 -> 0 | G35: =ICMS!G29 -> 0 | H35: =ICMS!H29 -> 0 | I35: =ICMS!I29 -> 0 | J35: =ICMS!J29 -> 0 | K35: =ICMS!K29 -> 0 | L35: =ICMS!L29 -> 0 | M35: =ICMS!M29 -> 0 | ... Q35: =ICMS!Q29 -> 0 | R35: =SUM(F35:Q35) -> 0
C36: PIS | F36: =-TRUNC(F$34*$E22,2) -> 0 | G36: =-TRUNC(G$34*$E22,2) -> 0 | H36: =-TRUNC(H$34*$E22,2) -> 0 | I36: =-TRUNC(I$34*$E22,2) -> 0 | J36: =-TRUNC(J$34*$E22,2) -> 0 | K36: =-TRUNC(K$34*$E22,2) -> 0 | L36: =-TRUNC(L$34*$E22,2) -> 0 | M36: =-TRUNC(M$34*$E22,2) -> 0 | ... Q36: =-TRUNC(Q$34*$E22,2) -> 0 | R36: =SUM(F36:Q36) -> 0
C37: Cofins | F37: =-TRUNC(F$34*$E23,2) -> 0 | G37: =-TRUNC(G$34*$E23,2) -> 0 | H37: =-TRUNC(H$34*$E23,2) -> 0 | I37: =-TRUNC(I$34*$E23,2) -> 0 | J37: =-TRUNC(J$34*$E23,2) -> 0 | K37: =-TRUNC(K$34*$E23,2) -> 0 | L37: =-TRUNC(L$34*$E23,2) -> 0 | M37: =-TRUNC(M$34*$E23,2) -> 0 | ... Q37: =-TRUNC(Q$34*$E23,2) -> 0 | R37: =SUM(F37:Q37) -> 0
C38: Base de Cálculo (apenas ITX/EILD) | F38: =SUM(F34:F37) -> 0 | G38: =SUM(G34:G37) -> 0 | H38: =SUM(H34:H37) -> 0 | I38: =SUM(I34:I37) -> 0 | J38: =SUM(J34:J37) -> 0 | K38: =SUM(K34:K37) -> 0 | L38: =SUM(L34:L37) -> 0 | M38: =SUM(M34:M37) -> 0 | ... Q38: =SUM(Q34:Q37) -> 0 | R38: =SUM(F38:Q38) -> 0
C39: Fust | E39: 0.01 | F39: =-TRUNC(F$38*$E39,2) -> 0 | G39: =-TRUNC(G$38*$E39,2) -> 0 | H39: =-TRUNC(H$38*$E39,2) -> 0 | I39: =-TRUNC(I$38*$E39,2) -> 0 | J39: =-TRUNC(J$38*$E39,2) -> 0 | K39: =-TRUNC(K$38*$E39,2) -> 0 | L39: =-TRUNC(L$38*$E39,2) -> 0 | M39: =-TRUNC(M$38*$E39,2) -> 0 | ... Q39: =-TRUNC(Q$38*$E39,2) -> 0 | R39: =SUM(F39:Q39) -> 0
C40: Funttel | E40: 0.005 | F40: =-TRUNC(F$38*$E40,2) -> 0 | G40: =-TRUNC(G$38*$E40,2) -> 0 | H40: =-TRUNC(H$38*$E40,2) -> 0 | I40: =-TRUNC(I$38*$E40,2) -> 0 | J40: =-TRUNC(J$38*$E40,2) -> 0 | K40: =-TRUNC(K$38*$E40,2) -> 0 | L40: =-TRUNC(L$38*$E40,2) -> 0 | M40: =-TRUNC(M$38*$E40,2) -> 0 | ... Q40: =-TRUNC(Q$38*$E40,2) -> 0 | R40: =SUM(F40:Q40) -> 0
C43: Resumo para planilha de upload
C44: TOTAL
C45: Receita operacional bruta: | F45: =F18 -> 0 | G45: =G18 -> 0 | H45: =H18 -> 0 | I45: =I18 -> 0 | J45: =J18 -> 0 | K45: =K18 -> 0 | L45: =L18 -> 0 | M45: =M18 -> 0 | ... Q45: =Q18 -> 0
C46: ICMS: | F46: =-F21 -> 0 | G46: =-G21 -> 0 | H46: =-H21 -> 0 | I46: =-I21 -> 0 | J46: =-J21 -> 0 | K46: =-K21 -> 0 | L46: =-L21 -> 0 | M46: =-M21 -> 0 | ... Q46: =-Q21 -> 0
C47: PIS: | F47: =-F22 -> 0 | G47: =-G22 -> 0 | H47: =-H22 -> 0 | I47: =-I22 -> 0 | J47: =-J22 -> 0 | K47: =-K22 -> 0 | L47: =-L22 -> 0 | M47: =-M22 -> 0 | ... Q47: =-Q22 -> 0
C48: COFINS: | F48: =-F23 -> 0 | G48: =-G23 -> 0 | H48: =-H23 -> 0 | I48: =-I23 -> 0 | J48: =-J23 -> 0 | K48: =-K23 -> 0 | L48: =-L23 -> 0 | M48: =-M23 -> 0 | ... Q48: =-Q23 -> 0
C50: APENAS INTERCONEXÃO/EILD
C51: Receita operacional bruta: | F51: =F34 -> 0 | G51: =G34 -> 0 | H51: =H34 -> 0 | I51: =I34 -> 0 | J51: =J34 -> 0 | K51: =K34 -> 0 | L51: =L34 -> 0 | M51: =M34 -> 0 | ... Q51: =Q34 -> 0
C52: ICMS: | F52: =-F35 -> 0 | G52: =-G35 -> 0 | H52: =-H35 -> 0 | I52: =-I35 -> 0 | J52: =-J35 -> 0 | K52: =-K35 -> 0 | L52: =-L35 -> 0 | M52: =-M35 -> 0 | ... Q52: =-Q35 -> 0
C53: PIS: | F53: =-F36 -> 0 | G53: =-G36 -> 0 | H53: =-H36 -> 0 | I53: =-I36 -> 0 | J53: =-J36 -> 0 | K53: =-K36 -> 0 | L53: =-L36 -> 0 | M53: =-M36 -> 0 | ... Q53: =-Q36 -> 0
C54: COFINS: | F54: =-F37 -> 0 | G54: =-G37 -> 0 | H54: =-H37 -> 0 | I54: =-I37 -> 0 | J54: =-J37 -> 0 | K54: =-K37 -> 0 | L54: =-L37 -> 0 | M54: =-M37 -> 0 | ... Q54: =-Q37 -> 0
D56: ITX
D57: EILD

Sheet ICMS
B1: =Apuração!B1 -> Ano fiscal: | C1: =Apuração!C1 -> 2022
B2: =Apuração!B2:C2 -> CÁLCULO DO FUST/FUNTTEL - ANO 2022 | D2: ITX / | E2: =Apuração!E2 -> ICMS | F2: CÁLCULO DO ICMS A ABATER | R2: TOTAL ANUAL | T2: ALÍQUOTAS MENSAIS MÉDIAS (pro rata temporis)
B3: CODIGO | C3: CONTA | D3: EILD? | E3: =Apuração!E3 -> UF | F3: =Apuração!F3 -> 44562 | G3: =Apuração!G3 -> 44593 | H3: =Apuração!H3 -> 44621 | I3: =Apuração!I3 -> 44652 | J3: =Apuração!J3 -> 44682 | K3: =Apuração!K3 -> 44713 | L3: =Apuração!L3 -> 44743 | ... Q3: =Apuração!Q3 -> 44896 | T3: =F3 -> 44562 | U3: =G3 -> 44593 | V3: =H3 -> 44621 | W3: =I3 -> 44652 | X3: =J3 -> 44682 | Y3: =K3 -> 44713 | Z3: =L3 -> 44743 | AA3: =M3 -> 44774 | ... AE3: =Q3 -> 44896
B5: (A) Receita
B6: =Apuração!B6 -> 0 | C6: =Apuração!C6 -> 0 | D6: =Apuração!D6 -> 0 | E6: =Apuração!E6 -> 0 | F6: =-TRUNC(Apuração!F6*T6,2) -> 0 | G6: =-TRUNC(Apuração!G6*U6,2) -> 0 | H6: =-TRUNC(Apuração!H6*V6,2) -> 0 | I6: =-TRUNC(Apuração!I6*W6,2) -> 0 | J6: =-TRUNC(Apuração!J6*X6,2) -> 0 | K6: =-TRUNC(Apuração!K6*Y6,2) -> 0 | L6: =-TRUNC(Apuração!L6*Z6,2) -> 0 | M6: =-TRUNC(Apuração!M6*AA6,2) -> 0 | ... Q6: =-TRUNC(Apuração!Q6*AE6,2) -> 0 | R6: =SUM(F6:Q6) -> 0 | T6: =IF(OR($D6="ITX",$E6="NT"),0,IF($E$3="UF",_xlfn.XLOOKUP($E6,'Tabela mensal ICMS'!$B$34:$B$63,'Tabela mensal ICMS'!D$34:D$63,0),$E6)) -> 0 | U6: =IF(OR($D6="ITX",$E6="NT"),0,IF($E$3="UF",_xlfn.XLOOKUP($E6,'Tabela mensal ICMS'!$B$34:$B$63,'Tabela mensal ICMS'!E$34:E$63,0),$E6)) -> 0 | V6: =IF(OR($D6="ITX",$E6="NT"),0,IF($E$3="UF",_xlfn.XLOOKUP($E6,'Tabela mensal ICMS'!$B$34:$B$63,'Tabela mensal ICMS'!F$34:F$63,0),$E6)) -> 0 | W6: =IF(OR($D6="ITX",$E6="NT"),0,IF($E$3="UF",_xlfn.XLOOKUP($E6,'Tabela mensal ICMS'!$B$34:$B$63,'Tabela mensal ICMS'!G$34:G$63,0),$E6)) -> 0 | X6: =IF(OR($D6="ITX",$E6="NT"),0,IF($E$3="UF",_xlfn.XLOOKUP($E6,'Tabela mensal ICMS'!$B$34:$B$63,'Tabela mensal ICMS'!H$34:H$63,0),$E6)) -> 0 | Y6: =IF(OR($D6="ITX",$E6="NT"),0,IF($E$3="UF",_xlfn.XLOOKUP($E6,'Tabela mensal ICMS'!$B$34:$B$63,'Tabela mensal ICMS'!I$34:I$63,0),$E6)) -> 0 | Z6: =IF(OR($D6="ITX",$E6="NT"),0,IF($E$3="UF",_xlfn.XLOOKUP($E6,'Tabela mensal ICMS'!$B$34:$B$63,'Tabela mensal ICMS'!J$34:J$63,0),$E6)) -> 0 | AA6: =IF(OR($D6="ITX",$E6="NT"),0,IF($E$3="UF",_xlfn.XLOOKUP($E6,'Tabela mensal ICMS'!$B$34:$B$63,'Tabela mensal ICMS'!K$34:K$63,0),$E6)) -> 0 | ... AE6: =IF(OR($D6="ITX",$E6="NT"),0,IF($E$3="UF",_xlfn.XLOOKUP($E6,'Tabela mensal ICMS'!$B$34:$B$63,'Tabela mensal ICMS'!O$34:O$63,0),$E6)) -> 0
B7: =Apuração!B7 -> 0 | C7: =Apuração!C7 -> 0 | D7: =Apuração!D7 -> 0 | E7: =Apuração!E7 -> 0 | F7: =-TRUNC(Apuração!F7*T7,2) -> 0 | G7: =-TRUNC(Apuração!G7*U7,2) -> 0 | H7: =-TRUNC(Apuração!H7*V7,2) -> 0 | I7: =-TRUNC(Apuração!I7*W7,2) -> 0 | J7: =-TRUNC(Apuração!J7*X7,2) -> 0 | K7: =-TRUNC(Apuração!K7*Y7,2) -> 0 | L7: =-TRUNC(Apuração!L7*Z7,2) -> 0 | M7: =-TRUNC(Apuração!M7*AA7,2) -> 0 | ... Q7: =-TRUNC(Apuração!Q7*AE7,2) -> 0 | R7: =SUM(F7:Q7) -> 0 | T7: =IF(OR($D7="ITX",$E7="NT"),0,IF($E$3="UF",_xlfn.XLOOKUP($E7,'Tabela mensal ICMS'!$B$34:$B$63,'Tabela mensal ICMS'!D$34:D$63,0),$E7)) -> 0 | U7: =IF(OR($D7="ITX",$E7="NT"),0,IF($E$3="UF",_xlfn.XLOOKUP($E7,'Tabela mensal ICMS'!$B$34:$B$63,'Tabela mensal ICMS'!E$34:E$63,0),$E7)) -> 0 | V7: =IF(OR($D7="ITX",$E7="NT"),0,IF($E$3="UF",_xlfn.XLOOKUP($E7,'Tabela mensal ICMS'!$B$34:$B$63,'Tabela mensal ICMS'!F$34:F$63,0),$E7)) -> 0 | W7: =IF(OR($D7="ITX",$E7="NT"),0,IF($E$3="UF",_xlfn.XLOOKUP($E7,'Tabela mensal ICMS'!$B$34:$B$63,'Tabela mensal ICMS'!G$34:G$63,0),$E7)) -> 0 | X7: =IF(OR($D7="ITX",$E7="NT"),0,IF($E$3="UF",_xlfn.XLOOKUP($E7,'Tabela mensal ICMS'!$B$34:$B$63,'Tabela mensal ICMS'!H$34:H$63,0),$E7)) -> 0 | Y7: =IF(OR($D7="ITX",$E7="NT"),0,IF($E$3="UF",_xlfn.XLOOKUP($E7,'Tabela mensal ICMS'!$B$34:$B$63,'Tabela mensal ICMS'!I$34:I$63,0),$E7)) -> 0 | Z7: =IF(OR($D7="ITX",$E7="NT"),0,IF($E$3="UF",_xlfn.XLOOKUP($E7,'Tabela mensal ICMS'!$B$34:$B$63,'Tabela mensal ICMS'!J$34:J$63,0),$E7)) -> 0 | AA7: =IF(OR($D7="ITX",$E7="NT"),0,IF($E$3="UF",_xlfn.XLOOKUP($E7,'Tabela mensal ICMS'!$B$34:$B$63,'Tabela mensal ICMS'!K$34:K$63,0),$E7)) -> 0 | ... AE7: =IF(OR($D7="ITX",$E7="NT"),0,IF($E$3="UF",_xlfn.XLOOKUP($E7,'Tabela mensal ICMS'!$B$34:$B$63,'Tabela mensal ICMS'!O$34:O$63,0),$E7)) -> 0
B8: =Apuração!B8 -> 0 | C8: =Apuração!C8 -> 0 | D8: =Apuração!D8 -> 0 | E8: =Apuração!E8 -> 0 | F8: =-TRUNC(Apuração!F8*T8,2) -> 0 | G8: =-TRUNC(Apuração!G8*U8,2) -> 0 | H8: =-TRUNC(Apuração!H8*V8,2) -> 0 | I8: =-TRUNC(Apuração!I8*W8,2) -> 0 | J8: =-TRUNC(Apuração!J8*X8,2) -> 0 | K8: =-TRUNC(Apuração!K8*Y8,2) -> 0 | L8: =-TRUNC(Apuração!L8*Z8,2) -> 0 | M8: =-TRUNC(Apuração!M8*AA8,2) -> 0 | ... Q8: =-TRUNC(Apuração!Q8*AE8,2) -> 0 | R8: =SUM(F8:Q8) -> 0 | T8: =IF(OR($D8="ITX",$E8="NT"),0,IF($E$3="UF",_xlfn.XLOOKUP($E8,'Tabela mensal ICMS'!$B$34:$B$63,'Tabela mensal ICMS'!D$34:D$63,0),$E8)) -> 0 | U8: =IF(OR($D8="ITX",$E8="NT"),0,IF($E$3="UF",_xlfn.XLOOKUP($E8,'Tabela mensal ICMS'!$B$34:$B$63,'Tabela mensal ICMS'!E$34:E$63,0),$E8)) -> 0 | V8: =IF(OR($D8="ITX",$E8="NT"),0,IF($E$3="UF",_xlfn.XLOOKUP($E8,'Tabela mensal ICMS'!$B$34:$B$63,'Tabela mensal ICMS'!F$34:F$63,0),$E8)) -> 0 | W8: =IF(OR($D8="ITX",$E8="NT"),0,IF($E$3="UF",_xlfn.XLOOKUP($E8,'Tabela mensal ICMS'!$B$34:$B$63,'Tabela mensal ICMS'!G$34:G$63,0),$E8)) -> 0 | X8: =IF(OR($D8="ITX",$E8="NT"),0,IF($E$3="UF",_xlfn.XLOOKUP($E8,'Tabela mensal ICMS'!$B$34:$B$63,'Tabela mensal ICMS'!H$34:H$63,0),$E8)) -> 0 | Y8: =IF(OR($D8="ITX",$E8="NT"),0,IF($E$3="UF",_xlfn.XLOOKUP($E8,'Tabela mensal ICMS'!$B$34:$B$63,'Tabela mensal ICMS'!I$34:I$63,0),$E8)) -> 0 | Z8: =IF(OR($D8="ITX",$E8="NT"),0,IF($E$3="UF",_xlfn.XLOOKUP($E8,'Tabela mensal ICMS'!$B$34:$B$63,'Tabela mensal ICMS'!J$34:J$63,0),$E8)) -> 0 | AA8: =IF(OR($D8="ITX",$E8="NT"),0,IF($E$3="UF",_xlfn.XLOOKUP($E8,'Tabela mensal ICMS'!$B$34:$B$63,'Tabela mensal ICMS'!K$34:K$63,0),$E8)) -> 0 | ... AE8: =IF(OR($D8="ITX",$E8="NT"),0,IF($E$3="UF",_xlfn.XLOOKUP($E8,'Tabela mensal ICMS'!$B$34:$B$63,'Tabela mensal ICMS'!O$34:O$63,0),$E8)) -> 0
B9: =Apuração!B9 -> 0 | C9: =Apuração!C9 -> 0 | D9: =Apuração!D9 -> 0 | E9: =Apuração!E9 -> 0 | F9: =-TRUNC(Apuração!F9*T9,2) -> 0 | G9: =-TRUNC(Apuração!G9*U9,2) -> 0 | H9: =-TRUNC(Apuração!H9*V9,2) -> 0 | I9: =-TRUNC(Apuração!I9*W9,2) -> 0 | J9: =-TRUNC(Apuração!J9*X9,2) -> 0 | K9: =-TRUNC(Apuração!K9*Y9,2) -> 0 | L9: =-TRUNC(Apuração!L9*Z9,2) -> 0 | M9: =-TRUNC(Apuração!M9*AA9,2) -> 0 | ... Q9: =-TRUNC(Apuração!Q9*AE9,2) -> 0 | R9: =SUM(F9:Q9) -> 0 | T9: =IF(OR($D9="ITX",$E9="NT"),0,IF($E$3="UF",_xlfn.XLOOKUP($E9,'Tabela mensal ICMS'!$B$34:$B$63,'Tabela mensal ICMS'!D$34:D$63,0),$E9)) -> 0 | U9: =IF(OR($D9="ITX",$E9="NT"),0,IF($E$3="UF",_xlfn.XLOOKUP($E9,'Tabela mensal ICMS'!$B$34:$B$63,'Tabela mensal ICMS'!E$34:E$63,0),$E9)) -> 0 | V9: =IF(OR($D9="ITX",$E9="NT"),0,IF($E$3="UF",_xlfn.XLOOKUP($E9,'Tabela mensal ICMS'!$B$34:$B$63,'Tabela mensal ICMS'!F$34:F$63,0),$E9)) -> 0 | W9: =IF(OR($D9="ITX",$E9="NT"),0,IF($E$3="UF",_xlfn.XLOOKUP($E9,'Tabela mensal ICMS'!$B$34:$B$63,'Tabela mensal ICMS'!G$34:G$63,0),$E9)) -> 0 | X9: =IF(OR($D9="ITX",$E9="NT"),0,IF($E$3="UF",_xlfn.XLOOKUP($E9,'Tabela mensal ICMS'!$B$34:$B$63,'Tabela mensal ICMS'!H$34:H$63,0),$E9)) -> 0 | Y9: =IF(OR($D9="ITX",$E9="NT"),0,IF($E$3="UF",_xlfn.XLOOKUP($E9,'Tabela mensal ICMS'!$B$34:$B$63,'Tabela mensal ICMS'!I$34:I$63,0),$E9)) -> 0 | Z9: =IF(OR($D9="ITX",$E9="NT"),0,IF($E$3="UF",_xlfn.XLOOKUP($E9,'Tabela mensal ICMS'!$B$34:$B$63,'Tabela mensal ICMS'!J$34:J$63,0),$E9)) -> 0 | AA9: =IF(OR($D9="ITX",$E9="NT"),0,IF($E$3="UF",_xlfn.XLOOKUP($E9,'Tabela mensal ICMS'!$B$34:$B$63,'Tabela mensal ICMS'!K$34:K$63,0),$E9)) -> 0 | ... AE9: =IF(OR($D9="ITX",$E9="NT"),0,IF($E$3="UF",_xlfn.XLOOKUP($E9,'Tabela mensal ICMS'!$B$34:$B$63,'Tabela mensal ICMS'!O$34:O$63,0),$E9)) -> 0
B10: =Apuração!B10 -> 0 | C10: =Apuração!C10 -> 0 | D10: =Apuração!D10 -> 0 | E10: =Apuração!E10 -> 0 | F10: =-TRUNC(Apuração!F10*T10,2) -> 0 | G10: =-TRUNC(Apuração!G10*U10,2) -> 0 | H10: =-TRUNC(Apuração!H10*V10,2) -> 0 | I10: =-TRUNC(Apuração!I10*W10,2) -> 0 | J10: =-TRUNC(Apuração!J10*X10,2) -> 0 | K10: =-TRUNC(Apuração!K10*Y10,2) -> 0 | L10: =-TRUNC(Apuração!L10*Z10,2) -> 0 | M10: =-TRUNC(Apuração!M10*AA10,2) -> 0 | ... Q10: =-TRUNC(Apuração!Q10*AE10,2) -> 0 | R10: =SUM(F10:Q10) -> 0 | T10: =IF(OR($D10="ITX",$E10="NT"),0,IF($E$3="UF",_xlfn.XLOOKUP($E10,'Tabela mensal ICMS'!$B$34:$B$63,'Tabela mensal ICMS'!D$34:D$63,0),$E10)) -> 0 | U10: =IF(OR($D10="ITX",$E10="NT"),0,IF($E$3="UF",_xlfn.XLOOKUP($E10,'Tabela mensal ICMS'!$B$34:$B$63,'Tabela mensal ICMS'!E$34:E$63,0),$E10)) -> 0 | V10: =IF(OR($D10="ITX",$E10="NT"),0,IF($E$3="UF",_xlfn.XLOOKUP($E10,'Tabela mensal ICMS'!$B$34:$B$63,'Tabela mensal ICMS'!F$34:F$63,0),$E10)) -> 0 | W10: =IF(OR($D10="ITX",$E10="NT"),0,IF($E$3="UF",_xlfn.XLOOKUP($E10,'Tabela mensal ICMS'!$B$34:$B$63,'Tabela mensal ICMS'!G$34:G$63,0),$E10)) -> 0 | X10: =IF(OR($D10="ITX",$E10="NT"),0,IF($E$3="UF",_xlfn.XLOOKUP($E10,'Tabela mensal ICMS'!$B$34:$B$63,'Tabela mensal ICMS'!H$34:H$63,0),$E10)) -> 0 | Y10: =IF(OR($D10="ITX",$E10="NT"),0,IF($E$3="UF",_xlfn.XLOOKUP($E10,'Tabela mensal ICMS'!$B$34:$B$63,'Tabela mensal ICMS'!I$34:I$63,0),$E10)) -> 0 | Z10: =IF(OR($D10="ITX",$E10="NT"),0,IF($E$3="UF",_xlfn.XLOOKUP($E10,'Tabela mensal ICMS'!$B$34:$B$63,'Tabela mensal ICMS'!J$34:J$63,0),$E10)) -> 0 | AA10: =IF(OR($D10="ITX",$E10="NT"),0,IF($E$3="UF",_xlfn.XLOOKUP($E10,'Tabela mensal ICMS'!$B$34:$B$63,'Tabela mensal ICMS'!K$34:K$63,0),$E10)) -> 0 | ... AE10: =IF(OR($D10="ITX",$E10="NT"),0,IF($E$3="UF",_xlfn.XLOOKUP($E10,'Tabela mensal ICMS'!$B$34:$B$63,'Tabela mensal ICMS'!O$34:O$63,0),$E10)) -> 0
B11: TOTAL (A) | F11: =SUM(F6:F10) -> 0 | G11: =SUM(G6:G10) -> 0 | H11: =SUM(H6:H10) -> 0 | I11: =SUM(I6:I10) -> 0 | J11: =SUM(J6:J10) -> 0 | K11: =SUM(K6:K10) -> 0 | L11: =SUM(L6:L10) -> 0 | M11: =SUM(M6:M10) -> 0 | ... R11: =SUM(R6:R10) -> 0
B12: (B) Cancelamentos e descontos incondicionais
B13: =Apuração!B13 -> 0 | C13: =Apuração!C13 -> 0 | D13: =Apuração!D13 -> 0 | E13: =Apuração!E13 -> 0 | F13: =-TRUNC(Apuração!F13*$E13,2) -> 0 | G13: =-TRUNC(Apuração!G13*$E13,2) -> 0 | H13: =-TRUNC(Apuração!H13*$E13,2) -> 0 | I13: =-TRUNC(Apuração!I13*$E13,2) -> 0 | J13: =-TRUNC(Apuração!J13*$E13,2) -> 0 | K13: =-TRUNC(Apuração!K13*$E13,2) -> 0 | L13: =-TRUNC(Apuração!L13*$E13,2) -> 0 | M13: =-TRUNC(Apuração!M13*$E13,2) -> 0 | ... Q13: =-TRUNC(Apuração!Q13*$E13,2) -> 0 | R13: =SUM(F13:Q13) -> 0 | T13: =IF(OR($D13="ITX",$E13="NT"),0,IF($E$3="UF",_xlfn.XLOOKUP($E13,'Tabela mensal ICMS'!$B$34:$B$63,'Tabela mensal ICMS'!D$34:D$63,0),$E13)) -> 0 | U13: =IF(OR($D13="ITX",$E13="NT"),0,IF($E$3="UF",_xlfn.XLOOKUP($E13,'Tabela mensal ICMS'!$B$34:$B$63,'Tabela mensal ICMS'!E$34:E$63,0),$E13)) -> 0 | V13: =IF(OR($D13="ITX",$E13="NT"),0,IF($E$3="UF",_xlfn.XLOOKUP($E13,'Tabela mensal ICMS'!$B$34:$B$63,'Tabela mensal ICMS'!F$34:F$63,0),$E13)) -> 0 | W13: =IF(OR($D13="ITX",$E13="NT"),0,IF($E$3="UF",_xlfn.XLOOKUP($E13,'Tabela mensal ICMS'!$B$34:$B$63,'Tabela mensal ICMS'!G$34:G$63,0),$E13)) -> 0 | X13: =IF(OR($D13="ITX",$E13="NT"),0,IF($E$3="UF",_xlfn.XLOOKUP($E13,'Tabela mensal ICMS'!$B$34:$B$63,'Tabela mensal ICMS'!H$34:H$63,0),$E13)) -> 0 | Y13: =IF(OR($D13="ITX",$E13="NT"),0,IF($E$3="UF",_xlfn.XLOOKUP($E13,'Tabela mensal ICMS'!$B$34:$B$63,'Tabela mensal ICMS'!I$34:I$63,0),$E13)) -> 0 | Z13: =IF(OR($D13="ITX",$E13="NT"),0,IF($E$3="UF",_xlfn.XLOOKUP($E13,'Tabela mensal ICMS'!$B$34:$B$63,'Tabela mensal ICMS'!J$34:J$63,0),$E13)) -> 0 | AA13: =IF(OR($D13="ITX",$E13="NT"),0,IF($E$3="UF",_xlfn.XLOOKUP($E13,'Tabela mensal ICMS'!$B$34:$B$63,'Tabela mensal ICMS'!K$34:K$63,0),$E13)) -> 0 | ... AE13: =IF(OR($D13="ITX",$E13="NT"),0,IF($E$3="UF",_xlfn.XLOOKUP($E13,'Tabela mensal ICMS'!$B$34:$B$63,'Tabela mensal ICMS'!O$34:O$63,0),$E13)) -> 0
B14: =Apuração!B14 -> 0 | C14: =Apuração!C14 -> 0 | D14: =Apuração!D14 -> 0 | E14: =Apuração!E14 -> 0 | F14: =-TRUNC(Apuração!F14*$E14,2) -> 0 | G14: =-TRUNC(Apuração!G14*$E14,2) -> 0 | H14: =-TRUNC(Apuração!H14*$E14,2) -> 0 | I14: =-TRUNC(Apuração!I14*$E14,2) -> 0 | J14: =-TRUNC(Apuração!J14*$E14,2) -> 0 | K14: =-TRUNC(Apuração!K14*$E14,2) -> 0 | L14: =-TRUNC(Apuração!L14*$E14,2) -> 0 | M14: =-TRUNC(Apuração!M14*$E14,2) -> 0 | ... Q14: =-TRUNC(Apuração!Q14*$E14,2) -> 0 | R14: =SUM(F14:Q14) -> 0 | T14: =IF(OR($D14="ITX",$E14="NT"),0,IF($E$3="UF",_xlfn.XLOOKUP($E14,'Tabela mensal ICMS'!$B$34:$B$63,'Tabela mensal ICMS'!D$34:D$63,0),$E14)) -> 0 | U14: =IF(OR($D14="ITX",$E14="NT"),0,IF($E$3="UF",_xlfn.XLOOKUP($E14,'Tabela mensal ICMS'!$B$34:$B$63,'Tabela mensal ICMS'!E$34:E$63,0),$E14)) -> 0 | V14: =IF(OR($D14="ITX",$E14="NT"),0,IF($E$3="UF",_xlfn.XLOOKUP($E14,'Tabela mensal ICMS'!$B$34:$B$63,'Tabela mensal ICMS'!F$34:F$63,0),$E14)) -> 0 | W14: =IF(OR($D14="ITX",$E14="NT"),0,IF($E$3="UF",_xlfn.XLOOKUP($E14,'Tabela mensal ICMS'!$B$34:$B$63,'Tabela mensal ICMS'!G$34:G$63,0),$E14)) -> 0 | X14: =IF(OR($D14="ITX",$E14="NT"),0,IF($E$3="UF",_xlfn.XLOOKUP($E14,'Tabela mensal ICMS'!$B$34:$B$63,'Tabela mensal ICMS'!H$34:H$63,0),$E14)) -> 0 | Y14: =IF(OR($D14="ITX",$E14="NT"),0,IF($E$3="UF",_xlfn.XLOOKUP($E14,'Tabela mensal ICMS'!$B$34:$B$63,'Tabela mensal ICMS'!I$34:I$63,0),$E14)) -> 0 | Z14: =IF(OR($D14="ITX",$E14="NT"),0,IF($E$3="UF",_xlfn.XLOOKUP($E14,'Tabela mensal ICMS'!$B$34:$B$63,'Tabela mensal ICMS'!J$34:J$63,0),$E14)) -> 0 | AA14: =IF(OR($D14="ITX",$E14="NT"),0,IF($E$3="UF",_xlfn.XLOOKUP($E14,'Tabela mensal ICMS'!$B$34:$B$63,'Tabela mensal ICMS'!K$34:K$63,0),$E14)) -> 0 | ... AE14: =IF(OR($D14="ITX",$E14="NT"),0,IF($E$3="UF",_xlfn.XLOOKUP($E14,'Tabela mensal ICMS'!$B$34:$B$63,'Tabela mensal ICMS'!O$34:O$63,0),$E14)) -> 0
B15: =Apuração!B15 -> 0 | C15: =Apuração!C15 -> 0 | D15: =Apuração!D15 -> 0 | E15: =Apuração!E15 -> 0 | F15: =-TRUNC(Apuração!F15*$E15,2) -> 0 | G15: =-TRUNC(Apuração!G15*$E15,2) -> 0 | H15: =-TRUNC(Apuração!H15*$E15,2) -> 0 | I15: =-TRUNC(Apuração!I15*$E15,2) -> 0 | J15: =-TRUNC(Apuração!J15*$E15,2) -> 0 | K15: =-TRUNC(Apuração!K15*$E15,2) -> 0 | L15: =-TRUNC(Apuração!L15*$E15,2) -> 0 | M15: =-TRUNC(Apuração!M15*$E15,2) -> 0 | ... Q15: =-TRUNC(Apuração!Q15*$E15,2) -> 0 | R15: =SUM(F15:Q15) -> 0 | T15: =IF(OR($D15="ITX",$E15="NT"),0,IF($E$3="UF",_xlfn.XLOOKUP($E15,'Tabela mensal ICMS'!$B$34:$B$63,'Tabela mensal ICMS'!D$34:D$63,0),$E15)) -> 0 | U15: =IF(OR($D15="ITX",$E15="NT"),0,IF($E$3="UF",_xlfn.XLOOKUP($E15,'Tabela mensal ICMS'!$B$34:$B$63,'Tabela mensal ICMS'!E$34:E$63,0),$E15)) -> 0 | V15: =IF(OR($D15="ITX",$E15="NT"),0,IF($E$3="UF",_xlfn.XLOOKUP($E15,'Tabela mensal ICMS'!$B$34:$B$63,'Tabela mensal ICMS'!F$34:F$63,0),$E15)) -> 0 | W15: =IF(OR($D15="ITX",$E15="NT"),0,IF($E$3="UF",_xlfn.XLOOKUP($E15,'Tabela mensal ICMS'!$B$34:$B$63,'Tabela mensal ICMS'!G$34:G$63,0),$E15)) -> 0 | X15: =IF(OR($D15="ITX",$E15="NT"),0,IF($E$3="UF",_xlfn.XLOOKUP($E15,'Tabela mensal ICMS'!$B$34:$B$63,'Tabela mensal ICMS'!H$34:H$63,0),$E15)) -> 0 | Y15: =IF(OR($D15="ITX",$E15="NT"),0,IF($E$3="UF",_xlfn.XLOOKUP($E15,'Tabela mensal ICMS'!$B$34:$B$63,'Tabela mensal ICMS'!I$34:I$63,0),$E15)) -> 0 | Z15: =IF(OR($D15="ITX",$E15="NT"),0,IF($E$3="UF",_xlfn.XLOOKUP($E15,'Tabela mensal ICMS'!$B$34:$B$63,'Tabela mensal ICMS'!J$34:J$63,0),$E15)) -> 0 | AA15: =IF(OR($D15="ITX",$E15="NT"),0,IF($E$3="UF",_xlfn.XLOOKUP($E15,'Tabela mensal ICMS'!$B$34:$B$63,'Tabela mensal ICMS'!K$34:K$63,0),$E15)) -> 0 | ... AE15: =IF(OR($D15="ITX",$E15="NT"),0,IF($E$3="UF",_xlfn.XLOOKUP($E15,'Tabela mensal ICMS'!$B$34:$B$63,'Tabela mensal ICMS'!O$34:O$63,0),$E15)) -> 0
B16: TOTAL (B) | F16: =SUM(F13:F15) -> 0 | G16: =SUM(G13:G15) -> 0 | H16: =SUM(H13:H15) -> 0 | I16: =SUM(I13:I15) -> 0 | J16: =SUM(J13:J15) -> 0 | K16: =SUM(K13:K15) -> 0 | L16: =SUM(L13:L15) -> 0 | M16: =SUM(M13:M15) -> 0 | ... R16: =SUM(R13:R15) -> 0
C18: (A) + (B) | F18: =F11+F16 -> 0 | G18: =G11+G16 -> 0 | H18: =H11+H16 -> 0 | I18: =I11+I16 -> 0 | J18: =J11+J16 -> 0 | K18: =K11+K16 -> 0 | L18: =L11+L16 -> 0 | M18: =M11+M16 -> 0 | ... R18: =R11+R16 -> 0
B20: ICMS contabilizado
R21: =SUM(F21:Q21) -> 0
R22: =SUM(F22:Q22) -> 0
R23: =SUM(F23:Q23) -> 0
C24: TOTAL | F24: =SUM(F21:F23) -> 0 | G24: =SUM(G21:G23) -> 0 | H24: =SUM(H21:H23) -> 0 | I24: =SUM(I21:I23) -> 0 | J24: =SUM(J21:J23) -> 0 | K24: =SUM(K21:K23) -> 0 | L24: =SUM(L21:L23) -> 0 | M24: =SUM(M21:M23) -> 0 | ... R24: =SUM(R21:R23) -> 0
B26: ICMS estimado x contabilizado | F26: =IF(ABS($R$24)<ABS($R$18),F24,F18) -> 0 | G26: =IF(ABS($R$24)<ABS($R$18),G24,G18) -> 0 | H26: =IF(ABS($R$24)<ABS($R$18),H24,H18) -> 0 | I26: =IF(ABS($R$24)<ABS($R$18),I24,I18) -> 0 | J26: =IF(ABS($R$24)<ABS($R$18),J24,J18) -> 0 | K26: =IF(ABS($R$24)<ABS($R$18),K24,K18) -> 0 | L26: =IF(ABS($R$24)<ABS($R$18),L24,L18) -> 0 | M26: =IF(ABS($R$24)<ABS($R$18),M24,M18) -> 0 | ... Q26: =IF(ABS($R$24)<ABS($R$18),Q24,Q18) -> 0 | R26: =SUM(F26:Q26) -> 0
B27: (dos dois o menor)
B29: ICMS estimado x contabilizado (apenas ITX/EILD) | F29: =IF(ABS(SUMIFS($R$21:$R$23,$D$21:$D$23,"ITX")+SUMIFS($R$21:$R$23,$D$21:$D$23,"EILD"))<ABS(SUMIFS($R$6:$R$15,$D$6:$D$15,"ITX")+SUMIFS($R$6:$R$15,$D$6:$D$15,"EILD")),SUMIFS(F$21:F$23,$D$21:$D$23,"ITX")+SUMIFS(F$21:F$23,$D$21:$D$23,"EILD"),SUMIFS(F$6:F$15,$D$6:$D$15,"ITX")+SUMIFS(F$6:F$15,$D$6:$D$15,"EILD")) -> 0 | G29: =IF(ABS(SUMIFS($R$21:$R$23,$D$21:$D$23,"ITX")+SUMIFS($R$21:$R$23,$D$21:$D$23,"EILD"))<ABS(SUMIFS($R$6:$R$15,$D$6:$D$15,"ITX")+SUMIFS($R$6:$R$15,$D$6:$D$15,"EILD")),SUMIFS(G$21:G$23,$D$21:$D$23,"ITX")+SUMIFS(G$21:G$23,$D$21:$D$23,"EILD"),SUMIFS(G$6:G$15,$D$6:$D$15,"ITX")+SUMIFS(G$6:G$15,$D$6:$D$15,"EILD")) -> 0 | H29: =IF(ABS(SUMIFS($R$21:$R$23,$D$21:$D$23,"ITX")+SUMIFS($R$21:$R$23,$D$21:$D$23,"EILD"))<ABS(SUMIFS($R$6:$R$15,$D$6:$D$15,"ITX")+SUMIFS($R$6:$R$15,$D$6:$D$15,"EILD")),SUMIFS(H$21:H$23,$D$21:$D$23,"ITX")+SUMIFS(H$21:H$23,$D$21:$D$23,"EILD"),SUMIFS(H$6:H$15,$D$6:$D$15,"ITX")+SUMIFS(H$6:H$15,$D$6:$D$15,"EILD")) -> 0 | I29: =IF(ABS(SUMIFS($R$21:$R$23,$D$21:$D$23,"ITX")+SUMIFS($R$21:$R$23,$D$21:$D$23,"EILD"))<ABS(SUMIFS($R$6:$R$15,$D$6:$D$15,"ITX")+SUMIFS($R$6:$R$15,$D$6:$D$15,"EILD")),SUMIFS(I$21:I$23,$D$21:$D$23,"ITX")+SUMIFS(I$21:I$23,$D$21:$D$23,"EILD"),SUMIFS(I$6:I$15,$D$6:$D$15,"ITX")+SUMIFS(I$6:I$15,$D$6:$D$15,"EILD")) -> 0 | J29: =IF(ABS(SUMIFS($R$21:$R$23,$D$21:$D$23,"ITX")+SUMIFS($R$21:$R$23,$D$21:$D$23,"EILD"))<ABS(SUMIFS($R$6:$R$15,$D$6:$D$15,"ITX")+SUMIFS($R$6:$R$15,$D$6:$D$15,"EILD")),SUMIFS(J$21:J$23,$D$21:$D$23,"ITX")+SUMIFS(J$21:J$23,$D$21:$D$23,"EILD"),SUMIFS(J$6:J$15,$D$6:$D$15,"ITX")+SUMIFS(J$6:J$15,$D$6:$D$15,"EILD")) -> 0 | K29: =IF(ABS(SUMIFS($R$21:$R$23,$D$21:$D$23,"ITX")+SUMIFS($R$21:$R$23,$D$21:$D$23,"EILD"))<ABS(SUMIFS($R$6:$R$15,$D$6:$D$15,"ITX")+SUMIFS($R$6:$R$15,$D$6:$D$15,"EILD")),SUMIFS(K$21:K$23,$D$21:$D$23,"ITX")+SUMIFS(K$21:K$23,$D$21:$D$23,"EILD"),SUMIFS(K$6:K$15,$D$6:$D$15,"ITX")+SUMIFS(K$6:K$15,$D$6:$D$15,"EILD")) -> 0 | L29: =IF(ABS(SUMIFS($R$21:$R$23,$D$21:$D$23,"ITX")+SUMIFS($R$21:$R$23,$D$21:$D$23,"EILD"))<ABS(SUMIFS($R$6:$R$15,$D$6:$D$15,"ITX")+SUMIFS($R$6:$R$15,$D$6:$D$15,"EILD")),SUMIFS(L$21:L$23,$D$21:$D$23,"ITX")+SUMIFS(L$21:L$23,$D$21:$D$23,"EILD"),SUMIFS(L$6:L$15,$D$6:$D$15,"ITX")+SUMIFS(L$6:L$15,$D$6:$D$15,"EILD")) -> 0 | M29: =IF(ABS(SUMIFS($R$21:$R$23,$D$21:$D$23,"ITX")+SUMIFS($R$21:$R$23,$D$21:$D$23,"EILD"))<ABS(SUMIFS($R$6:$R$15,$D$6:$D$15,"ITX")+SUMIFS($R$6:$R$15,$D$6:$D$15,"EILD")),SUMIFS(M$21:M$23,$D$21:$D$23,"ITX")+SUMIFS(M$21:M$23,$D$21:$D$23,"EILD"),SUMIFS(M$6:M$15,$D$6:$D$15,"ITX")+SUMIFS(M$6:M$15,$D$6:$D$15,"EILD")) -> 0 | ... Q29: =IF(ABS(SUMIFS($R$21:$R$23,$D$21:$D$23,"ITX")+SUMIFS($R$21:$R$23,$D$21:$D$23,"EILD"))<ABS(SUMIFS($R$6:$R$15,$D$6:$D$15,"ITX")+SUMIFS($R$6:$R$15,$D$6:$D$15,"EILD")),SUMIFS(Q$21:Q$23,$D$21:$D$23,"ITX")+SUMIFS(Q$21:Q$23,$D$21:$D$23,"EILD"),SUMIFS(Q$6:Q$15,$D$6:$D$15,"ITX")+SUMIFS(Q$6:Q$15,$D$6:$D$15,"EILD")) -> 0 | R29: =SUM(F29:Q29) -> 0
B30: (dos dois o menor)

Sheet Tabela mensal ICMS
B2: Ano: | D2: =Apuração!C1 -> 2022 | V2: 2022
B3: Alíquotas ao final de cada mês (*valores totais já com eventuais adicionais dos Fundos estaduais de combate a pobreza) | V3: 2023
B4: UF | C4: =EOMONTH(D4,-1) -> 44561 | D4: =DATE($D$2,1,1) -> 44562 | E4: =DATE($D$2,2,1) -> 44593 | F4: =DATE($D$2,3,1) -> 44621 | G4: =DATE($D$2,4,1) -> 44652 | H4: =DATE($D$2,5,1) -> 44682 | I4: =DATE($D$2,6,1) -> 44713 | J4: =DATE($D$2,7,1) -> 44743 | K4: =DATE($D$2,8,1) -> 44774 | L4: =DATE($D$2,9,1) -> 44805 | M4: =DATE($D$2,10,1) -> 44835 | N4: =DATE($D$2,11,1) -> 44866 | O4: =DATE($D$2,12,1) -> 44896 | V4: 2024
B5: ='Alíquotas ICMS'!B5 -> AC | C5: =IF('Alíquotas ICMS'!$K5<=EOMONTH(C$4,0),'Alíquotas ICMS'!$L5,IF('Alíquotas ICMS'!$I5<=EOMONTH(C$4,0),'Alíquotas ICMS'!$J5,IF('Alíquotas ICMS'!$G5<=EOMONTH(C$4,0),'Alíquotas ICMS'!$H5,'Alíquotas ICMS'!$F5))) -> 0.25 | D5: =IF('Alíquotas ICMS'!$K5<=EOMONTH(D$4,0),'Alíquotas ICMS'!$L5,IF('Alíquotas ICMS'!$I5<=EOMONTH(D$4,0),'Alíquotas ICMS'!$J5,IF('Alíquotas ICMS'!$G5<=EOMONTH(D$4,0),'Alíquotas ICMS'!$H5,'Alíquotas ICMS'!$F5))) -> 0.25 | E5: =IF('Alíquotas ICMS'!$K5<=EOMONTH(E$4,0),'Alíquotas ICMS'!$L5,IF('Alíquotas ICMS'!$I5<=EOMONTH(E$4,0),'Alíquotas ICMS'!$J5,IF('Alíquotas ICMS'!$G5<=EOMONTH(E$4,0),'Alíquotas ICMS'!$H5,'Alíquotas ICMS'!$F5))) -> 0.25 | F5: =IF('Alíquotas ICMS'!$K5<=EOMONTH(F$4,0),'Alíquotas ICMS'!$L5,IF('Alíquotas ICMS'!$I5<=EOMONTH(F$4,0),'Alíquotas ICMS'!$J5,IF('Alíquotas ICMS'!$G5<=EOMONTH(F$4,0),'Alíquotas ICMS'!$H5,'Alíquotas ICMS'!$F5))) -> 0.25 | G5: =IF('Alíquotas ICMS'!$K5<=EOMONTH(G$4,0),'Alíquotas ICMS'!$L5,IF('Alíquotas ICMS'!$I5<=EOMONTH(G$4,0),'Alíquotas ICMS'!$J5,IF('Alíquotas ICMS'!$G5<=EOMONTH(G$4,0),'Alíquotas ICMS'!$H5,'Alíquotas ICMS'!$F5))) -> 0.25 | H5: =IF('Alíquotas ICMS'!$K5<=EOMONTH(H$4,0),'Alíquotas ICMS'!$L5,IF('Alíquotas ICMS'!$I5<=EOMONTH(H$4,0),'Alíquotas ICMS'!$J5,IF('Alíquotas ICMS'!$G5<=EOMONTH(H$4,0),'Alíquotas ICMS'!$H5,'Alíquotas ICMS'!$F5))) -> 0.25 | I5: =IF('Alíquotas ICMS'!$K5<=EOMONTH(I$4,0),'Alíquotas ICMS'!$L5,IF('Alíquotas ICMS'!$I5<=EOMONTH(I$4,0),'Alíquotas ICMS'!$J5,IF('Alíquotas ICMS'!$G5<=EOMONTH(I$4,0),'Alíquotas ICMS'!$H5,'Alíquotas ICMS'!$F5))) -> 0.25 | J5: =IF('Alíquotas ICMS'!$K5<=EOMONTH(J$4,0),'Alíquotas ICMS'!$L5,IF('Alíquotas ICMS'!$I5<=EOMONTH(J$4,0),'Alíquotas ICMS'!$J5,IF('Alíquotas ICMS'!$G5<=EOMONTH(J$4,0),'Alíquotas ICMS'!$H5,'Alíquotas ICMS'!$F5))) -> 0.17 | ... O5: =IF('Alíquotas ICMS'!$K5<=EOMONTH(O$4,0),'Alíquotas ICMS'!$L5,IF('Alíquotas ICMS'!$I5<=EOMONTH(O$4,0),'Alíquotas ICMS'!$J5,IF('Alíquotas ICMS'!$G5<=EOMONTH(O$4,0),'Alíquotas ICMS'!$H5,'Alíquotas ICMS'!$F5))) -> 0.17
B6: ='Alíquotas ICMS'!B6 -> AL | C6: =IF('Alíquotas ICMS'!$K6<=EOMONTH(C$4,0),'Alíquotas ICMS'!$L6,IF('Alíquotas ICMS'!$I6<=EOMONTH(C$4,0),'Alíquotas ICMS'!$J6,IF('Alíquotas ICMS'!$G6<=EOMONTH(C$4,0),'Alíquotas ICMS'!$H6,'Alíquotas ICMS'!$F6))) -> 0.3 | D6: =IF('Alíquotas ICMS'!$K6<=EOMONTH(D$4,0),'Alíquotas ICMS'!$L6,IF('Alíquotas ICMS'!$I6<=EOMONTH(D$4,0),'Alíquotas ICMS'!$J6,IF('Alíquotas ICMS'!$G6<=EOMONTH(D$4,0),'Alíquotas ICMS'!$H6,'Alíquotas ICMS'!$F6))) -> 0.3 | E6: =IF('Alíquotas ICMS'!$K6<=EOMONTH(E$4,0),'Alíquotas ICMS'!$L6,IF('Alíquotas ICMS'!$I6<=EOMONTH(E$4,0),'Alíquotas ICMS'!$J6,IF('Alíquotas ICMS'!$G6<=EOMONTH(E$4,0),'Alíquotas ICMS'!$H6,'Alíquotas ICMS'!$F6))) -> 0.3 | F6: =IF('Alíquotas ICMS'!$K6<=EOMONTH(F$4,0),'Alíquotas ICMS'!$L6,IF('Alíquotas ICMS'!$I6<=EOMONTH(F$4,0),'Alíquotas ICMS'!$J6,IF('Alíquotas ICMS'!$G6<=EOMONTH(F$4,0),'Alíquotas ICMS'!$H6,'Alíquotas ICMS'!$F6))) -> 0.3 | G6: =IF('Alíquotas ICMS'!$K6<=EOMONTH(G$4,0),'Alíquotas ICMS'!$L6,IF('Alíquotas ICMS'!$I6<=EOMONTH(G$4,0),'Alíquotas ICMS'!$J6,IF('Alíquotas ICMS'!$G6<=EOMONTH(G$4,0),'Alíquotas ICMS'!$H6,'Alíquotas ICMS'!$F6))) -> 0.3 | H6: =IF('Alíquotas ICMS'!$K6<=EOMONTH(H$4,0),'Alíquotas ICMS'!$L6,IF('Alíquotas ICMS'!$I6<=EOMONTH(H$4,0),'Alíquotas ICMS'!$J6,IF('Alíquotas ICMS'!$G6<=EOMONTH(H$4,0),'Alíquotas ICMS'!$H6,'Alíquotas ICMS'!$F6))) -> 0.3 | I6: =IF('Alíquotas ICMS'!$K6<=EOMONTH(I$4,0),'Alíquotas ICMS'!$L6,IF('Alíquotas ICMS'!$I6<=EOMONTH(I$4,0),'Alíquotas ICMS'!$J6,IF('Alíquotas ICMS'!$G6<=EOMONTH(I$4,0),'Alíquotas ICMS'!$H6,'Alíquotas ICMS'!$F6))) -> 0.3 | J6: =IF('Alíquotas ICMS'!$K6<=EOMONTH(J$4,0),'Alíquotas ICMS'!$L6,IF('Alíquotas ICMS'!$I6<=EOMONTH(J$4,0),'Alíquotas ICMS'!$J6,IF('Alíquotas ICMS'!$G6<=EOMONTH(J$4,0),'Alíquotas ICMS'!$H6,'Alíquotas ICMS'!$F6))) -> 0.19 | ... O6: =IF('Alíquotas ICMS'!$K6<=EOMONTH(O$4,0),'Alíquotas ICMS'!$L6,IF('Alíquotas ICMS'!$I6<=EOMONTH(O$4,0),'Alíquotas ICMS'!$J6,IF('Alíquotas ICMS'!$G6<=EOMONTH(O$4,0),'Alíquotas ICMS'!$H6,'Alíquotas ICMS'!$F6))) -> 0.19
B7: ='Alíquotas ICMS'!B7 -> AM | C7: =IF('Alíquotas ICMS'!$K7<=EOMONTH(C$4,0),'Alíquotas ICMS'!$L7,IF('Alíquotas ICMS'!$I7<=EOMONTH(C$4,0),'Alíquotas ICMS'!$J7,IF('Alíquotas ICMS'!$G7<=EOMONTH(C$4,0),'Alíquotas ICMS'!$H7,'Alíquotas ICMS'!$F7))) -> 0.3 | D7: =IF('Alíquotas ICMS'!$K7<=EOMONTH(D$4,0),'Alíquotas ICMS'!$L7,IF('Alíquotas ICMS'!$I7<=EOMONTH(D$4,0),'Alíquotas ICMS'!$J7,IF('Alíquotas ICMS'!$G7<=EOMONTH(D$4,0),'Alíquotas ICMS'!$H7,'Alíquotas ICMS'!$F7))) -> 0.3 | E7: =IF('Alíquotas ICMS'!$K7<=EOMONTH(E$4,0),'Alíquotas ICMS'!$L7,IF('Alíquotas ICMS'!$I7<=EOMONTH(E$4,0),'Alíquotas ICMS'!$J7,IF('Alíquotas ICMS'!$G7<=EOMONTH(E$4,0),'Alíquotas ICMS'!$H7,'Alíquotas ICMS'!$F7))) -> 0.3 | F7: =IF('Alíquotas ICMS'!$K7<=EOMONTH(F$4,0),'Alíquotas ICMS'!$L7,IF('Alíquotas ICMS'!$I7<=EOMONTH(F$4,0),'Alíquotas ICMS'!$J7,IF('Alíquotas ICMS'!$G7<=EOMONTH(F$4,0),'Alíquotas ICMS'!$H7,'Alíquotas ICMS'!$F7))) -> 0.3 | G7: =IF('Alíquotas ICMS'!$K7<=EOMONTH(G$4,0),'Alíquotas ICMS'!$L7,IF('Alíquotas ICMS'!$I7<=EOMONTH(G$4,0),'Alíquotas ICMS'!$J7,IF('Alíquotas ICMS'!$G7<=EOMONTH(G$4,0),'Alíquotas ICMS'!$H7,'Alíquotas ICMS'!$F7))) -> 0.3 | H7: =IF('Alíquotas ICMS'!$K7<=EOMONTH(H$4,0),'Alíquotas ICMS'!$L7,IF('Alíquotas ICMS'!$I7<=EOMONTH(H$4,0),'Alíquotas ICMS'!$J7,IF('Alíquotas ICMS'!$G7<=EOMONTH(H$4,0),'Alíquotas ICMS'!$H7,'Alíquotas ICMS'!$F7))) -> 0.3 | I7: =IF('Alíquotas ICMS'!$K7<=EOMONTH(I$4,0),'Alíquotas ICMS'!$L7,IF('Alíquotas ICMS'!$I7<=EOMONTH(I$4,0),'Alíquotas ICMS'!$J7,IF('Alíquotas ICMS'!$G7<=EOMONTH(I$4,0),'Alíquotas ICMS'!$H7,'Alíquotas ICMS'!$F7))) -> 0.3 | J7: =IF('Alíquotas ICMS'!$K7<=EOMONTH(J$4,0),'Alíquotas ICMS'!$L7,IF('Alíquotas ICMS'!$I7<=EOMONTH(J$4,0),'Alíquotas ICMS'!$J7,IF('Alíquotas ICMS'!$G7<=EOMONTH(J$4,0),'Alíquotas ICMS'!$H7,'Alíquotas ICMS'!$F7))) -> 0.18 | ... O7: =IF('Alíquotas ICMS'!$K7<=EOMONTH(O$4,0),'Alíquotas ICMS'!$L7,IF('Alíquotas ICMS'!$I7<=EOMONTH(O$4,0),'Alíquotas ICMS'!$J7,IF('Alíquotas ICMS'!$G7<=EOMONTH(O$4,0),'Alíquotas ICMS'!$H7,'Alíquotas ICMS'!$F7))) -> 0.18
B8: ='Alíquotas ICMS'!B8 -> AP | C8: =IF('Alíquotas ICMS'!$K8<=EOMONTH(C$4,0),'Alíquotas ICMS'!$L8,IF('Alíquotas ICMS'!$I8<=EOMONTH(C$4,0),'Alíquotas ICMS'!$J8,IF('Alíquotas ICMS'!$G8<=EOMONTH(C$4,0),'Alíquotas ICMS'!$H8,'Alíquotas ICMS'!$F8))) -> 0.29 | D8: =IF('Alíquotas ICMS'!$K8<=EOMONTH(D$4,0),'Alíquotas ICMS'!$L8,IF('Alíquotas ICMS'!$I8<=EOMONTH(D$4,0),'Alíquotas ICMS'!$J8,IF('Alíquotas ICMS'!$G8<=EOMONTH(D$4,0),'Alíquotas ICMS'!$H8,'Alíquotas ICMS'!$F8))) -> 0.29 | E8: =IF('Alíquotas ICMS'!$K8<=EOMONTH(E$4,0),'Alíquotas ICMS'!$L8,IF('Alíquotas ICMS'!$I8<=EOMONTH(E$4,0),'Alíquotas ICMS'!$J8,IF('Alíquotas ICMS'!$G8<=EOMONTH(E$4,0),'Alíquotas ICMS'!$H8,'Alíquotas ICMS'!$F8))) -> 0.29 | F8: =IF('Alíquotas ICMS'!$K8<=EOMONTH(F$4,0),'Alíquotas ICMS'!$L8,IF('Alíquotas ICMS'!$I8<=EOMONTH(F$4,0),'Alíquotas ICMS'!$J8,IF('Alíquotas ICMS'!$G8<=EOMONTH(F$4,0),'Alíquotas ICMS'!$H8,'Alíquotas ICMS'!$F8))) -> 0.29 | G8: =IF('Alíquotas ICMS'!$K8<=EOMONTH(G$4,0),'Alíquotas ICMS'!$L8,IF('Alíquotas ICMS'!$I8<=EOMONTH(G$4,0),'Alíquotas ICMS'!$J8,IF('Alíquotas ICMS'!$G8<=EOMONTH(G$4,0),'Alíquotas ICMS'!$H8,'Alíquotas ICMS'!$F8))) -> 0.29 | H8: =IF('Alíquotas ICMS'!$K8<=EOMONTH(H$4,0),'Alíquotas ICMS'!$L8,IF('Alíquotas ICMS'!$I8<=EOMONTH(H$4,0),'Alíquotas ICMS'!$J8,IF('Alíquotas ICMS'!$G8<=EOMONTH(H$4,0),'Alíquotas ICMS'!$H8,'Alíquotas ICMS'!$F8))) -> 0.29 | I8: =IF('Alíquotas ICMS'!$K8<=EOMONTH(I$4,0),'Alíquotas ICMS'!$L8,IF('Alíquotas ICMS'!$I8<=EOMONTH(I$4,0),'Alíquotas ICMS'!$J8,IF('Alíquotas ICMS'!$G8<=EOMONTH(I$4,0),'Alíquotas ICMS'!$H8,'Alíquotas ICMS'!$F8))) -> 0.29 | J8: =IF('Alíquotas ICMS'!$K8<=EOMONTH(J$4,0),'Alíquotas ICMS'!$L8,IF('Alíquotas ICMS'!$I8<=EOMONTH(J$4,0),'Alíquotas ICMS'!$J8,IF('Alíquotas ICMS'!$G8<=EOMONTH(J$4,0),'Alíquotas ICMS'!$H8,'Alíquotas ICMS'!$F8))) -> 0.29 | ... O8: =IF('Alíquotas ICMS'!$K8<=EOMONTH(O$4,0),'Alíquotas ICMS'!$L8,IF('Alíquotas ICMS'!$I8<=EOMONTH(O$4,0),'Alíquotas ICMS'!$J8,IF('Alíquotas ICMS'!$G8<=EOMONTH(O$4,0),'Alíquotas ICMS'!$H8,'Alíquotas ICMS'!$F8))) -> 0.29
B9: ='Alíquotas ICMS'!B9 -> BA | C9: =IF('Alíquotas ICMS'!$K9<=EOMONTH(C$4,0),'Alíquotas ICMS'!$L9,IF('Alíquotas ICMS'!$I9<=EOMONTH(C$4,0),'Alíquotas ICMS'!$J9,IF('Alíquotas ICMS'!$G9<=EOMONTH(C$4,0),'Alíquotas ICMS'!$H9,'Alíquotas ICMS'!$F9))) -> 0.28 | D9: =IF('Alíquotas ICMS'!$K9<=EOMONTH(D$4,0),'Alíquotas ICMS'!$L9,IF('Alíquotas ICMS'!$I9<=EOMONTH(D$4,0),'Alíquotas ICMS'!$J9,IF('Alíquotas ICMS'!$G9<=EOMONTH(D$4,0),'Alíquotas ICMS'!$H9,'Alíquotas ICMS'!$F9))) -> 0.28 | E9: =IF('Alíquotas ICMS'!$K9<=EOMONTH(E$4,0),'Alíquotas ICMS'!$L9,IF('Alíquotas ICMS'!$I9<=EOMONTH(E$4,0),'Alíquotas ICMS'!$J9,IF('Alíquotas ICMS'!$G9<=EOMONTH(E$4,0),'Alíquotas ICMS'!$H9,'Alíquotas ICMS'!$F9))) -> 0.28 | F9: =IF('Alíquotas ICMS'!$K9<=EOMONTH(F$4,0),'Alíquotas ICMS'!$L9,IF('Alíquotas ICMS'!$I9<=EOMONTH(F$4,0),'Alíquotas ICMS'!$J9,IF('Alíquotas ICMS'!$G9<=EOMONTH(F$4,0),'Alíquotas ICMS'!$H9,'Alíquotas ICMS'!$F9))) -> 0.28 | G9: =IF('Alíquotas ICMS'!$K9<=EOMONTH(G$4,0),'Alíquotas ICMS'!$L9,IF('Alíquotas ICMS'!$I9<=EOMONTH(G$4,0),'Alíquotas ICMS'!$J9,IF('Alíquotas ICMS'!$G9<=EOMONTH(G$4,0),'Alíquotas ICMS'!$H9,'Alíquotas ICMS'!$F9))) -> 0.28 | H9: =IF('Alíquotas ICMS'!$K9<=EOMONTH(H$4,0),'Alíquotas ICMS'!$L9,IF('Alíquotas ICMS'!$I9<=EOMONTH(H$4,0),'Alíquotas ICMS'!$J9,IF('Alíquotas ICMS'!$G9<=EOMONTH(H$4,0),'Alíquotas ICMS'!$H9,'Alíquotas ICMS'!$F9))) -> 0.28 | I9: =IF('Alíquotas ICMS'!$K9<=EOMONTH(I$4,0),'Alíquotas ICMS'!$L9,IF('Alíquotas ICMS'!$I9<=EOMONTH(I$4,0),'Alíquotas ICMS'!$J9,IF('Alíquotas ICMS'!$G9<=EOMONTH(I$4,0),'Alíquotas ICMS'!$H9,'Alíquotas ICMS'!$F9))) -> 0.18 | J9: =IF('Alíquotas ICMS'!$K9<=EOMONTH(J$4,0),'Alíquotas ICMS'!$L9,IF('Alíquotas ICMS'!$I9<=EOMONTH(J$4,0),'Alíquotas ICMS'!$J9,IF('Alíquotas ICMS'!$G9<=EOMONTH(J$4,0),'Alíquotas ICMS'!$H9,'Alíquotas ICMS'!$F9))) -> 0.18 | ... O9: =IF('Alíquotas ICMS'!$K9<=EOMONTH(O$4,0),'Alíquotas ICMS'!$L9,IF('Alíquotas ICMS'!$I9<=EOMONTH(O$4,0),'Alíquotas ICMS'!$J9,IF('Alíquotas ICMS'!$G9<=EOMONTH(O$4,0),'Alíquotas ICMS'!$H9,'Alíquotas ICMS'!$F9))) -> 0.18
B10: ='Alíquotas ICMS'!B10 -> CE | C10: =IF('Alíquotas ICMS'!$K10<=EOMONTH(C$4,0),'Alíquotas ICMS'!$L10,IF('Alíquotas ICMS'!$I10<=EOMONTH(C$4,0),'Alíquotas ICMS'!$J10,IF('Alíquotas ICMS'!$G10<=EOMONTH(C$4,0),'Alíquotas ICMS'!$H10,'Alíquotas ICMS'!$F10))) -> 0.3 | D10: =IF('Alíquotas ICMS'!$K10<=EOMONTH(D$4,0),'Alíquotas ICMS'!$L10,IF('Alíquotas ICMS'!$I10<=EOMONTH(D$4,0),'Alíquotas ICMS'!$J10,IF('Alíquotas ICMS'!$G10<=EOMONTH(D$4,0),'Alíquotas ICMS'!$H10,'Alíquotas ICMS'!$F10))) -> 0.3 | E10: =IF('Alíquotas ICMS'!$K10<=EOMONTH(E$4,0),'Alíquotas ICMS'!$L10,IF('Alíquotas ICMS'!$I10<=EOMONTH(E$4,0),'Alíquotas ICMS'!$J10,IF('Alíquotas ICMS'!$G10<=EOMONTH(E$4,0),'Alíquotas ICMS'!$H10,'Alíquotas ICMS'!$F10))) -> 0.3 | F10: =IF('Alíquotas ICMS'!$K10<=EOMONTH(F$4,0),'Alíquotas ICMS'!$L10,IF('Alíquotas ICMS'!$I10<=EOMONTH(F$4,0),'Alíquotas ICMS'!$J10,IF('Alíquotas ICMS'!$G10<=EOMONTH(F$4,0),'Alíquotas ICMS'!$H10,'Alíquotas ICMS'!$F10))) -> 0.3 | G10: =IF('Alíquotas ICMS'!$K10<=EOMONTH(G$4,0),'Alíquotas ICMS'!$L10,IF('Alíquotas ICMS'!$I10<=EOMONTH(G$4,0),'Alíquotas ICMS'!$J10,IF('Alíquotas ICMS'!$G10<=EOMONTH(G$4,0),'Alíquotas ICMS'!$H10,'Alíquotas ICMS'!$F10))) -> 0.3 | H10: =IF('Alíquotas ICMS'!$K10<=EOMONTH(H$4,0),'Alíquotas ICMS'!$L10,IF('Alíquotas ICMS'!$I10<=EOMONTH(H$4,0),'Alíquotas ICMS'!$J10,IF('Alíquotas ICMS'!$G10<=EOMONTH(H$4,0),'Alíquotas ICMS'!$H10,'Alíquotas ICMS'!$F10))) -> 0.3 | I10: =IF('Alíquotas ICMS'!$K10<=EOMONTH(I$4,0),'Alíquotas ICMS'!$L10,IF('Alíquotas ICMS'!$I10<=EOMONTH(I$4,0),'Alíquotas ICMS'!$J10,IF('Alíquotas ICMS'!$G10<=EOMONTH(I$4,0),'Alíquotas ICMS'!$H10,'Alíquotas ICMS'!$F10))) -> 0.3 | J10: =IF('Alíquotas ICMS'!$K10<=EOMONTH(J$4,0),'Alíquotas ICMS'!$L10,IF('Alíquotas ICMS'!$I10<=EOMONTH(J$4,0),'Alíquotas ICMS'!$J10,IF('Alíquotas ICMS'!$G10<=EOMONTH(J$4,0),'Alíquotas ICMS'!$H10,'Alíquotas ICMS'!$F10))) -> 0.18 | ... O10: =IF('Alíquotas ICMS'!$K10<=EOMONTH(O$4,0),'Alíquotas ICMS'!$L10,IF('Alíquotas ICMS'!$I10<=EOMONTH(O$4,0),'Alíquotas ICMS'!$J10,IF('Alíquotas ICMS'!$G10<=EOMONTH(O$4,0),'Alíquotas ICMS'!$H10,'Alíquotas ICMS'!$F10))) -> 0.18
B11: ='Alíquotas ICMS'!B11 -> DF | C11: =IF('Alíquotas ICMS'!$K11<=EOMONTH(C$4,0),'Alíquotas ICMS'!$L11,IF('Alíquotas ICMS'!$I11<=EOMONTH(C$4,0),'Alíquotas ICMS'!$J11,IF('Alíquotas ICMS'!$G11<=EOMONTH(C$4,0),'Alíquotas ICMS'!$H11,'Alíquotas ICMS'!$F11))) -> 0.28 | D11: =IF('Alíquotas ICMS'!$K11<=EOMONTH(D$4,0),'Alíquotas ICMS'!$L11,IF('Alíquotas ICMS'!$I11<=EOMONTH(D$4,0),'Alíquotas ICMS'!$J11,IF('Alíquotas ICMS'!$G11<=EOMONTH(D$4,0),'Alíquotas ICMS'!$H11,'Alíquotas ICMS'!$F11))) -> 0.28 | E11: =IF('Alíquotas ICMS'!$K11<=EOMONTH(E$4,0),'Alíquotas ICMS'!$L11,IF('Alíquotas ICMS'!$I11<=EOMONTH(E$4,0),'Alíquotas ICMS'!$J11,IF('Alíquotas ICMS'!$G11<=EOMONTH(E$4,0),'Alíquotas ICMS'!$H11,'Alíquotas ICMS'!$F11))) -> 0.28 | F11: =IF('Alíquotas ICMS'!$K11<=EOMONTH(F$4,0),'Alíquotas ICMS'!$L11,IF('Alíquotas ICMS'!$I11<=EOMONTH(F$4,0),'Alíquotas ICMS'!$J11,IF('Alíquotas ICMS'!$G11<=EOMONTH(F$4,0),'Alíquotas ICMS'!$H11,'Alíquotas ICMS'!$F11))) -> 0.28 | G11: =IF('Alíquotas ICMS'!$K11<=EOMONTH(G$4,0),'Alíquotas ICMS'!$L11,IF('Alíquotas ICMS'!$I11<=EOMONTH(G$4,0),'Alíquotas ICMS'!$J11,IF('Alíquotas ICMS'!$G11<=EOMONTH(G$4,0),'Alíquotas ICMS'!$H11,'Alíquotas ICMS'!$F11))) -> 0.28 | H11: =IF('Alíquotas ICMS'!$K11<=EOMONTH(H$4,0),'Alíquotas ICMS'!$L11,IF('Alíquotas ICMS'!$I11<=EOMONTH(H$4,0),'Alíquotas ICMS'!$J11,IF('Alíquotas ICMS'!$G11<=EOMONTH(H$4,0),'Alíquotas ICMS'!$H11,'Alíquotas ICMS'!$F11))) -> 0.28 | I11: =IF('Alíquotas ICMS'!$K11<=EOMONTH(I$4,0),'Alíquotas ICMS'!$L11,IF('Alíquotas ICMS'!$I11<=EOMONTH(I$4,0),'Alíquotas ICMS'!$J11,IF('Alíquotas ICMS'!$G11<=EOMONTH(I$4,0),'Alíquotas ICMS'!$H11,'Alíquotas ICMS'!$F11))) -> 0.18 | J11: =IF('Alíquotas ICMS'!$K11<=EOMONTH(J$4,0),'Alíquotas ICMS'!$L11,IF('Alíquotas ICMS'!$I11<=EOMONTH(J$4,0),'Alíquotas ICMS'!$J11,IF('Alíquotas ICMS'!$G11<=EOMONTH(J$4,0),'Alíquotas ICMS'!$H11,'Alíquotas ICMS'!$F11))) -> 0.18 | ... O11: =IF('Alíquotas ICMS'!$K11<=EOMONTH(O$4,0),'Alíquotas ICMS'!$L11,IF('Alíquotas ICMS'!$I11<=EOMONTH(O$4,0),'Alíquotas ICMS'!$J11,IF('Alíquotas ICMS'!$G11<=EOMONTH(O$4,0),'Alíquotas ICMS'!$H11,'Alíquotas ICMS'!$F11))) -> 0.18
B12: ='Alíquotas ICMS'!B12 -> ES | C12: =IF('Alíquotas ICMS'!$K12<=EOMONTH(C$4,0),'Alíquotas ICMS'!$L12,IF('Alíquotas ICMS'!$I12<=EOMONTH(C$4,0),'Alíquotas ICMS'!$J12,IF('Alíquotas ICMS'!$G12<=EOMONTH(C$4,0),'Alíquotas ICMS'!$H12,'Alíquotas ICMS'!$F12))) -> 0.25 | D12: =IF('Alíquotas ICMS'!$K12<=EOMONTH(D$4,0),'Alíquotas ICMS'!$L12,IF('Alíquotas ICMS'!$I12<=EOMONTH(D$4,0),'Alíquotas ICMS'!$J12,IF('Alíquotas ICMS'!$G12<=EOMONTH(D$4,0),'Alíquotas ICMS'!$H12,'Alíquotas ICMS'!$F12))) -> 0.25 | E12: =IF('Alíquotas ICMS'!$K12<=EOMONTH(E$4,0),'Alíquotas ICMS'!$L12,IF('Alíquotas ICMS'!$I12<=EOMONTH(E$4,0),'Alíquotas ICMS'!$J12,IF('Alíquotas ICMS'!$G12<=EOMONTH(E$4,0),'Alíquotas ICMS'!$H12,'Alíquotas ICMS'!$F12))) -> 0.25 | F12: =IF('Alíquotas ICMS'!$K12<=EOMONTH(F$4,0),'Alíquotas ICMS'!$L12,IF('Alíquotas ICMS'!$I12<=EOMONTH(F$4,0),'Alíquotas ICMS'!$J12,IF('Alíquotas ICMS'!$G12<=EOMONTH(F$4,0),'Alíquotas ICMS'!$H12,'Alíquotas ICMS'!$F12))) -> 0.25 | G12: =IF('Alíquotas ICMS'!$K12<=EOMONTH(G$4,0),'Alíquotas ICMS'!$L12,IF('Alíquotas ICMS'!$I12<=EOMONTH(G$4,0),'Alíquotas ICMS'!$J12,IF('Alíquotas ICMS'!$G12<=EOMONTH(G$4,0),'Alíquotas ICMS'!$H12,'Alíquotas ICMS'!$F12))) -> 0.25 | H12: =IF('Alíquotas ICMS'!$K12<=EOMONTH(H$4,0),'Alíquotas ICMS'!$L12,IF('Alíquotas ICMS'!$I12<=EOMONTH(H$4,0),'Alíquotas ICMS'!$J12,IF('Alíquotas ICMS'!$G12<=EOMONTH(H$4,0),'Alíquotas ICMS'!$H12,'Alíquotas ICMS'!$F12))) -> 0.25 | I12: =IF('Alíquotas ICMS'!$K12<=EOMONTH(I$4,0),'Alíquotas ICMS'!$L12,IF('Alíquotas ICMS'!$I12<=EOMONTH(I$4,0),'Alíquotas ICMS'!$J12,IF('Alíquotas ICMS'!$G12<=EOMONTH(I$4,0),'Alíquotas ICMS'!$H12,'Alíquotas ICMS'!$F12))) -> 0.25 | J12: =IF('Alíquotas ICMS'!$K12<=EOMONTH(J$4,0),'Alíquotas ICMS'!$L12,IF('Alíquotas ICMS'!$I12<=EOMONTH(J$4,0),'Alíquotas ICMS'!$J12,IF('Alíquotas ICMS'!$G12<=EOMONTH(J$4,0),'Alíquotas ICMS'!$H12,'Alíquotas ICMS'!$F12))) -> 0.17 | ... O12: =IF('Alíquotas ICMS'!$K12<=EOMONTH(O$4,0),'Alíquotas ICMS'!$L12,IF('Alíquotas ICMS'!$I12<=EOMONTH(O$4,0),'Alíquotas ICMS'!$J12,IF('Alíquotas ICMS'!$G12<=EOMONTH(O$4,0),'Alíquotas ICMS'!$H12,'Alíquotas ICMS'!$F12))) -> 0.17
B13: ='Alíquotas ICMS'!B13 -> GO | C13: =IF('Alíquotas ICMS'!$K13<=EOMONTH(C$4,0),'Alíquotas ICMS'!$L13,IF('Alíquotas ICMS'!$I13<=EOMONTH(C$4,0),'Alíquotas ICMS'!$J13,IF('Alíquotas ICMS'!$G13<=EOMONTH(C$4,0),'Alíquotas ICMS'!$H13,'Alíquotas ICMS'!$F13))) -> 0.29 | D13: =IF('Alíquotas ICMS'!$K13<=EOMONTH(D$4,0),'Alíquotas ICMS'!$L13,IF('Alíquotas ICMS'!$I13<=EOMONTH(D$4,0),'Alíquotas ICMS'!$J13,IF('Alíquotas ICMS'!$G13<=EOMONTH(D$4,0),'Alíquotas ICMS'!$H13,'Alíquotas ICMS'!$F13))) -> 0.29 | E13: =IF('Alíquotas ICMS'!$K13<=EOMONTH(E$4,0),'Alíquotas ICMS'!$L13,IF('Alíquotas ICMS'!$I13<=EOMONTH(E$4,0),'Alíquotas ICMS'!$J13,IF('Alíquotas ICMS'!$G13<=EOMONTH(E$4,0),'Alíquotas ICMS'!$H13,'Alíquotas ICMS'!$F13))) -> 0.29 | F13: =IF('Alíquotas ICMS'!$K13<=EOMONTH(F$4,0),'Alíquotas ICMS'!$L13,IF('Alíquotas ICMS'!$I13<=EOMONTH(F$4,0),'Alíquotas ICMS'!$J13,IF('Alíquotas ICMS'!$G13<=EOMONTH(F$4,0),'Alíquotas ICMS'!$H13,'Alíquotas ICMS'!$F13))) -> 0.29 | G13: =IF('Alíquotas ICMS'!$K13<=EOMONTH(G$4,0),'Alíquotas ICMS'!$L13,IF('Alíquotas ICMS'!$I13<=EOMONTH(G$4,0),'Alíquotas ICMS'!$J13,IF('Alíquotas ICMS'!$G13<=EOMONTH(G$4,0),'Alíquotas ICMS'!$H13,'Alíquotas ICMS'!$F13))) -> 0.29 | H13: =IF('Alíquotas ICMS'!$K13<=EOMONTH(H$4,0),'Alíquotas ICMS'!$L13,IF('Alíquotas ICMS'!$I13<=EOMONTH(H$4,0),'Alíquotas ICMS'!$J13,IF('Alíquotas ICMS'!$G13<=EOMONTH(H$4,0),'Alíquotas ICMS'!$H13,'Alíquotas ICMS'!$F13))) -> 0.29 | I13: =IF('Alíquotas ICMS'!$K13<=EOMONTH(I$4,0),'Alíquotas ICMS'!$L13,IF('Alíquotas ICMS'!$I13<=EOMONTH(I$4,0),'Alíquotas ICMS'!$J13,IF('Alíquotas ICMS'!$G13<=EOMONTH(I$4,0),'Alíquotas ICMS'!$H13,'Alíquotas ICMS'!$F13))) -> 0.17 | J13: =IF('Alíquotas ICMS'!$K13<=EOMONTH(J$4,0),'Alíquotas ICMS'!$L13,IF('Alíquotas ICMS'!$I13<=EOMONTH(J$4,0),'Alíquotas ICMS'!$J13,IF('Alíquotas ICMS'!$G13<=EOMONTH(J$4,0),'Alíquotas ICMS'!$H13,'Alíquotas ICMS'!$F13))) -> 0.17 | ... O13: =IF('Alíquotas ICMS'!$K13<=EOMONTH(O$4,0),'Alíquotas ICMS'!$L13,IF('Alíquotas ICMS'!$I13<=EOMONTH(O$4,0),'Alíquotas ICMS'!$J13,IF('Alíquotas ICMS'!$G13<=EOMONTH(O$4,0),'Alíquotas ICMS'!$H13,'Alíquotas ICMS'!$F13))) -> 0.17
B14: ='Alíquotas ICMS'!B14 -> MA | C14: =IF('Alíquotas ICMS'!$K14<=EOMONTH(C$4,0),'Alíquotas ICMS'!$L14,IF('Alíquotas ICMS'!$I14<=EOMONTH(C$4,0),'Alíquotas ICMS'!$J14,IF('Alíquotas ICMS'!$G14<=EOMONTH(C$4,0),'Alíquotas ICMS'!$H14,'Alíquotas ICMS'!$F14))) -> 0.29 | D14: =IF('Alíquotas ICMS'!$K14<=EOMONTH(D$4,0),'Alíquotas ICMS'!$L14,IF('Alíquotas ICMS'!$I14<=EOMONTH(D$4,0),'Alíquotas ICMS'!$J14,IF('Alíquotas ICMS'!$G14<=EOMONTH(D$4,0),'Alíquotas ICMS'!$H14,'Alíquotas ICMS'!$F14))) -> 0.29 | E14: =IF('Alíquotas ICMS'!$K14<=EOMONTH(E$4,0),'Alíquotas ICMS'!$L14,IF('Alíquotas ICMS'!$I14<=EOMONTH(E$4,0),'Alíquotas ICMS'!$J14,IF('Alíquotas ICMS'!$G14<=EOMONTH(E$4,0),'Alíquotas ICMS'!$H14,'Alíquotas ICMS'!$F14))) -> 0.29 | F14: =IF('Alíquotas ICMS'!$K14<=EOMONTH(F$4,0),'Alíquotas ICMS'!$L14,IF('Alíquotas ICMS'!$I14<=EOMONTH(F$4,0),'Alíquotas ICMS'!$J14,IF('Alíquotas ICMS'!$G14<=EOMONTH(F$4,0),'Alíquotas ICMS'!$H14,'Alíquotas ICMS'!$F14))) -> 0.29 | G14: =IF('Alíquotas ICMS'!$K14<=EOMONTH(G$4,0),'Alíquotas ICMS'!$L14,IF('Alíquotas ICMS'!$I14<=EOMONTH(G$4,0),'Alíquotas ICMS'!$J14,IF('Alíquotas ICMS'!$G14<=EOMONTH(G$4,0),'Alíquotas ICMS'!$H14,'Alíquotas ICMS'!$F14))) -> 0.29 | H14: =IF('Alíquotas ICMS'!$K14<=EOMONTH(H$4,0),'Alíquotas ICMS'!$L14,IF('Alíquotas ICMS'!$I14<=EOMONTH(H$4,0),'Alíquotas ICMS'!$J14,IF('Alíquotas ICMS'!$G14<=EOMONTH(H$4,0),'Alíquotas ICMS'!$H14,'Alíquotas ICMS'!$F14))) -> 0.29 | I14: =IF('Alíquotas ICMS'!$K14<=EOMONTH(I$4,0),'Alíquotas ICMS'!$L14,IF('Alíquotas ICMS'!$I14<=EOMONTH(I$4,0),'Alíquotas ICMS'!$J14,IF('Alíquotas ICMS'!$G14<=EOMONTH(I$4,0),'Alíquotas ICMS'!$H14,'Alíquotas ICMS'!$F14))) -> 0.29 | J14: =IF('Alíquotas ICMS'!$K14<=EOMONTH(J$4,0),'Alíquotas ICMS'!$L14,IF('Alíquotas ICMS'!$I14<=EOMONTH(J$4,0),'Alíquotas ICMS'!$J14,IF('Alíquotas ICMS'!$G14<=EOMONTH(J$4,0),'Alíquotas ICMS'!$H14,'Alíquotas ICMS'!$F14))) -> 0.18 | ... O14: =IF('Alíquotas ICMS'!$K14<=EOMONTH(O$4,0),'Alíquotas ICMS'!$L14,IF('Alíquotas ICMS'!$I14<=EOMONTH(O$4,0),'Alíquotas ICMS'!$J14,IF('Alíquotas ICMS'!$G14<=EOMONTH(O$4,0),'Alíquotas ICMS'!$H14,'Alíquotas ICMS'!$F14))) -> 0.18
B15: ='Alíquotas ICMS'!B15 -> MG | C15: =IF('Alíquotas ICMS'!$K15<=EOMONTH(C$4,0),'Alíquotas ICMS'!$L15,IF('Alíquotas ICMS'!$I15<=EOMONTH(C$4,0),'Alíquotas ICMS'!$J15,IF('Alíquotas ICMS'!$G15<=EOMONTH(C$4,0),'Alíquotas ICMS'!$H15,'Alíquotas ICMS'!$F15))) -> 0.27 | D15: =IF('Alíquotas ICMS'!$K15<=EOMONTH(D$4,0),'Alíquotas ICMS'!$L15,IF('Alíquotas ICMS'!$I15<=EOMONTH(D$4,0),'Alíquotas ICMS'!$J15,IF('Alíquotas ICMS'!$G15<=EOMONTH(D$4,0),'Alíquotas ICMS'!$H15,'Alíquotas ICMS'!$F15))) -> 0.27 | E15: =IF('Alíquotas ICMS'!$K15<=EOMONTH(E$4,0),'Alíquotas ICMS'!$L15,IF('Alíquotas ICMS'!$I15<=EOMONTH(E$4,0),'Alíquotas ICMS'!$J15,IF('Alíquotas ICMS'!$G15<=EOMONTH(E$4,0),'Alíquotas ICMS'!$H15,'Alíquotas ICMS'!$F15))) -> 0.27 | F15: =IF('Alíquotas ICMS'!$K15<=EOMONTH(F$4,0),'Alíquotas ICMS'!$L15,IF('Alíquotas ICMS'!$I15<=EOMONTH(F$4,0),'Alíquotas ICMS'!$J15,IF('Alíquotas ICMS'!$G15<=EOMONTH(F$4,0),'Alíquotas ICMS'!$H15,'Alíquotas ICMS'!$F15))) -> 0.27 | G15: =IF('Alíquotas ICMS'!$K15<=EOMONTH(G$4,0),'Alíquotas ICMS'!$L15,IF('Alíquotas ICMS'!$I15<=EOMONTH(G$4,0),'Alíquotas ICMS'!$J15,IF('Alíquotas ICMS'!$G15<=EOMONTH(G$4,0),'Alíquotas ICMS'!$H15,'Alíquotas ICMS'!$F15))) -> 0.27 | H15: =IF('Alíquotas ICMS'!$K15<=EOMONTH(H$4,0),'Alíquotas ICMS'!$L15,IF('Alíquotas ICMS'!$I15<=EOMONTH(H$4,0),'Alíquotas ICMS'!$J15,IF('Alíquotas ICMS'!$G15<=EOMONTH(H$4,0),'Alíquotas ICMS'!$H15,'Alíquotas ICMS'!$F15))) -> 0.27 | I15: =IF('Alíquotas ICMS'!$K15<=EOMONTH(I$4,0),'Alíquotas ICMS'!$L15,IF('Alíquotas ICMS'!$I15<=EOMONTH(I$4,0),'Alíquotas ICMS'!$J15,IF('Alíquotas ICMS'!$G15<=EOMONTH(I$4,0),'Alíquotas ICMS'!$H15,'Alíquotas ICMS'!$F15))) -> 0.18 | J15: =IF('Alíquotas ICMS'!$K15<=EOMONTH(J$4,0),'Alíquotas ICMS'!$L15,IF('Alíquotas ICMS'!$I15<=EOMONTH(J$4,0),'Alíquotas ICMS'!$J15,IF('Alíquotas ICMS'!$G15<=EOMONTH(J$4,0),'Alíquotas ICMS'!$H15,'Alíquotas ICMS'!$F15))) -> 0.18 | ... O15: =IF('Alíquotas ICMS'!$K15<=EOMONTH(O$4,0),'Alíquotas ICMS'!$L15,IF('Alíquotas ICMS'!$I15<=EOMONTH(O$4,0),'Alíquotas ICMS'!$J15,IF('Alíquotas ICMS'!$G15<=EOMONTH(O$4,0),'Alíquotas ICMS'!$H15,'Alíquotas ICMS'!$F15))) -> 0.18
B16: ='Alíquotas ICMS'!B16 -> MS | C16: =IF('Alíquotas ICMS'!$K16<=EOMONTH(C$4,0),'Alíquotas ICMS'!$L16,IF('Alíquotas ICMS'!$I16<=EOMONTH(C$4,0),'Alíquotas ICMS'!$J16,IF('Alíquotas ICMS'!$G16<=EOMONTH(C$4,0),'Alíquotas ICMS'!$H16,'Alíquotas ICMS'!$F16))) -> 0.29 | D16: =IF('Alíquotas ICMS'!$K16<=EOMONTH(D$4,0),'Alíquotas ICMS'!$L16,IF('Alíquotas ICMS'!$I16<=EOMONTH(D$4,0),'Alíquotas ICMS'!$J16,IF('Alíquotas ICMS'!$G16<=EOMONTH(D$4,0),'Alíquotas ICMS'!$H16,'Alíquotas ICMS'!$F16))) -> 0.29 | E16: =IF('Alíquotas ICMS'!$K16<=EOMONTH(E$4,0),'Alíquotas ICMS'!$L16,IF('Alíquotas ICMS'!$I16<=EOMONTH(E$4,0),'Alíquotas ICMS'!$J16,IF('Alíquotas ICMS'!$G16<=EOMONTH(E$4,0),'Alíquotas ICMS'!$H16,'Alíquotas ICMS'!$F16))) -> 0.29 | F16: =IF('Alíquotas ICMS'!$K16<=EOMONTH(F$4,0),'Alíquotas ICMS'!$L16,IF('Alíquotas ICMS'!$I16<=EOMONTH(F$4,0),'Alíquotas ICMS'!$J16,IF('Alíquotas ICMS'!$G16<=EOMONTH(F$4,0),'Alíquotas ICMS'!$H16,'Alíquotas ICMS'!$F16))) -> 0.29 | G16: =IF('Alíquotas ICMS'!$K16<=EOMONTH(G$4,0),'Alíquotas ICMS'!$L16,IF('Alíquotas ICMS'!$I16<=EOMONTH(G$4,0),'Alíquotas ICMS'!$J16,IF('Alíquotas ICMS'!$G16<=EOMONTH(G$4,0),'Alíquotas ICMS'!$H16,'Alíquotas ICMS'!$F16))) -> 0.29 | H16: =IF('Alíquotas ICMS'!$K16<=EOMONTH(H$4,0),'Alíquotas ICMS'!$L16,IF('Alíquotas ICMS'!$I16<=EOMONTH(H$4,0),'Alíquotas ICMS'!$J16,IF('Alíquotas ICMS'!$G16<=EOMONTH(H$4,0),'Alíquotas ICMS'!$H16,'Alíquotas ICMS'!$F16))) -> 0.29 | I16: =IF('Alíquotas ICMS'!$K16<=EOMONTH(I$4,0),'Alíquotas ICMS'!$L16,IF('Alíquotas ICMS'!$I16<=EOMONTH(I$4,0),'Alíquotas ICMS'!$J16,IF('Alíquotas ICMS'!$G16<=EOMONTH(I$4,0),'Alíquotas ICMS'!$H16,'Alíquotas ICMS'!$F16))) -> 0.29 | J16: =IF('Alíquotas ICMS'!$K16<=EOMONTH(J$4,0),'Alíquotas ICMS'!$L16,IF('Alíquotas ICMS'!$I16<=EOMONTH(J$4,0),'Alíquotas ICMS'!$J16,IF('Alíquotas ICMS'!$G16<=EOMONTH(J$4,0),'Alíquotas ICMS'!$H16,'Alíquotas ICMS'!$F16))) -> 0.19 | ... O16: =IF('Alíquotas ICMS'!$K16<=EOMONTH(O$4,0),'Alíquotas ICMS'!$L16,IF('Alíquotas ICMS'!$I16<=EOMONTH(O$4,0),'Alíquotas ICMS'!$J16,IF('Alíquotas ICMS'!$G16<=EOMONTH(O$4,0),'Alíquotas ICMS'!$H16,'Alíquotas ICMS'!$F16))) -> 0.19
... B31: ='Alíquotas ICMS'!B31 -> TO | C31: =IF('Alíquotas ICMS'!$K31<=EOMONTH(C$4,0),'Alíquotas ICMS'!$L31,IF('Alíquotas ICMS'!$I31<=EOMONTH(C$4,0),'Alíquotas ICMS'!$J31,IF('Alíquotas ICMS'!$G31<=EOMONTH(C$4,0),'Alíquotas ICMS'!$H31,'Alíquotas ICMS'!$F31))) -> 0.29 | D31: =IF('Alíquotas ICMS'!$K31<=EOMONTH(D$4,0),'Alíquotas ICMS'!$L31,IF('Alíquotas ICMS'!$I31<=EOMONTH(D$4,0),'Alíquotas ICMS'!$J31,IF('Alíquotas ICMS'!$G31<=EOMONTH(D$4,0),'Alíquotas ICMS'!$H31,'Alíquotas ICMS'!$F31))) -> 0.29 | E31: =IF('Alíquotas ICMS'!$K31<=EOMONTH(E$4,0),'Alíquotas ICMS'!$L31,IF('Alíquotas ICMS'!$I31<=EOMONTH(E$4,0),'Alíquotas ICMS'!$J31,IF('Alíquotas ICMS'!$G31<=EOMONTH(E$4,0),'Alíquotas ICMS'!$H31,'Alíquotas ICMS'!$F31))) -> 0.29 | F31: =IF('Alíquotas ICMS'!$K31<=EOMONTH(F$4,0),'Alíquotas ICMS'!$L31,IF('Alíquotas ICMS'!$I31<=EOMONTH(F$4,0),'Alíquotas ICMS'!$J31,IF('Alíquotas ICMS'!$G31<=EOMONTH(F$4,0),'Alíquotas ICMS'!$H31,'Alíquotas ICMS'!$F31))) -> 0.29 | G31: =IF('Alíquotas ICMS'!$K31<=EOMONTH(G$4,0),'Alíquotas ICMS'!$L31,IF('Alíquotas ICMS'!$I31<=EOMONTH(G$4,0),'Alíquotas ICMS'!$J31,IF('Alíquotas ICMS'!$G31<=EOMONTH(G$4,0),'Alíquotas ICMS'!$H31,'Alíquotas ICMS'!$F31))) -> 0.29 | H31: =IF('Alíquotas ICMS'!$K31<=EOMONTH(H$4,0),'Alíquotas ICMS'!$L31,IF('Alíquotas ICMS'!$I31<=EOMONTH(H$4,0),'Alíquotas ICMS'!$J31,IF('Alíquotas ICMS'!$G31<=EOMONTH(H$4,0),'Alíquotas ICMS'!$H31,'Alíquotas ICMS'!$F31))) -> 0.29 | I31: =IF('Alíquotas ICMS'!$K31<=EOMONTH(I$4,0),'Alíquotas ICMS'!$L31,IF('Alíquotas ICMS'!$I31<=EOMONTH(I$4,0),'Alíquotas ICMS'!$J31,IF('Alíquotas ICMS'!$G31<=EOMONTH(I$4,0),'Alíquotas ICMS'!$H31,'Alíquotas ICMS'!$F31))) -> 0.29 | J31: =IF('Alíquotas ICMS'!$K31<=EOMONTH(J$4,0),'Alíquotas ICMS'!$L31,IF('Alíquotas ICMS'!$I31<=EOMONTH(J$4,0),'Alíquotas ICMS'!$J31,IF('Alíquotas ICMS'!$G31<=EOMONTH(J$4,0),'Alíquotas ICMS'!$H31,'Alíquotas ICMS'!$F31))) -> 0.29 | ... O31: =IF('Alíquotas ICMS'!$K31<=EOMONTH(O$4,0),'Alíquotas ICMS'!$L31,IF('Alíquotas ICMS'!$I31<=EOMONTH(O$4,0),'Alíquotas ICMS'!$J31,IF('Alíquotas ICMS'!$G31<=EOMONTH(O$4,0),'Alíquotas ICMS'!$H31,'Alíquotas ICMS'!$F31))) -> 0.18
B33: Alíquotas médias (ponderadas pelo número de dias em vigor)
B34: UF | D34: =DATE($D$2,1,1) -> 44562 | E34: =DATE($D$2,2,1) -> 44593 | F34: =DATE($D$2,3,1) -> 44621 | G34: =DATE($D$2,4,1) -> 44652 | H34: =DATE($D$2,5,1) -> 44682 | I34: =DATE($D$2,6,1) -> 44713 | J34: =DATE($D$2,7,1) -> 44743 | K34: =DATE($D$2,8,1) -> 44774 | L34: =DATE($D$2,9,1) -> 44805 | M34: =DATE($D$2,10,1) -> 44835 | N34: =DATE($D$2,11,1) -> 44866 | O34: =DATE($D$2,12,1) -> 44896
B35: n/d | D35: =MIN(D36:D62) -> 0.19 | E35: =MIN(E36:E62) -> 0.19 | F35: =MIN(F36:F62) -> 0.19 | G35: =MIN(G36:G62) -> 0.19 | H35: =MIN(H36:H62) -> 0.19 | I35: =MIN(I36:I62) -> 0.19 | J35: =MIN(J36:J62) -> 0.17 | K35: =MIN(K36:K62) -> 0.17 | ... O35: =MIN(O36:O62) -> 0.17
B36: =B5 -> AC | D36: =ROUND(((EOMONTH(D$4,0)-MAX(OFFSET('Alíquotas ICMS'!$E5,,MATCH(D5,'Alíquotas ICMS'!$E5:$L5,0)-2),D$4))*D5+(MAX(OFFSET('Alíquotas ICMS'!$E5,,MATCH(D5,'Alíquotas ICMS'!$E5:$L5,0)-2),D$4)-D$4)*C5)/(EOMONTH(D$4,0)-D$4),4) -> 0.25 | E36: =ROUND(((EOMONTH(E$4,0)-MAX(OFFSET('Alíquotas ICMS'!$E5,,MATCH(E5,'Alíquotas ICMS'!$E5:$L5,0)-2),E$4))*E5+(MAX(OFFSET('Alíquotas ICMS'!$E5,,MATCH(E5,'Alíquotas ICMS'!$E5:$L5,0)-2),E$4)-E$4)*D5)/(EOMONTH(E$4,0)-E$4),4) -> 0.25 | F36: =ROUND(((EOMONTH(F$4,0)-MAX(OFFSET('Alíquotas ICMS'!$E5,,MATCH(F5,'Alíquotas ICMS'!$E5:$L5,0)-2),F$4))*F5+(MAX(OFFSET('Alíquotas ICMS'!$E5,,MATCH(F5,'Alíquotas ICMS'!$E5:$L5,0)-2),F$4)-F$4)*E5)/(EOMONTH(F$4,0)-F$4),4) -> 0.25 | G36: =ROUND(((EOMONTH(G$4,0)-MAX(OFFSET('Alíquotas ICMS'!$E5,,MATCH(G5,'Alíquotas ICMS'!$E5:$L5,0)-2),G$4))*G5+(MAX(OFFSET('Alíquotas ICMS'!$E5,,MATCH(G5,'Alíquotas ICMS'!$E5:$L5,0)-2),G$4)-G$4)*F5)/(EOMONTH(G$4,0)-G$4),4) -> 0.25 | H36: =ROUND(((EOMONTH(H$4,0)-MAX(OFFSET('Alíquotas ICMS'!$E5,,MATCH(H5,'Alíquotas ICMS'!$E5:$L5,0)-2),H$4))*H5+(MAX(OFFSET('Alíquotas ICMS'!$E5,,MATCH(H5,'Alíquotas ICMS'!$E5:$L5,0)-2),H$4)-H$4)*G5)/(EOMONTH(H$4,0)-H$4),4) -> 0.25 | I36: =ROUND(((EOMONTH(I$4,0)-MAX(OFFSET('Alíquotas ICMS'!$E5,,MATCH(I5,'Alíquotas ICMS'!$E5:$L5,0)-2),I$4))*I5+(MAX(OFFSET('Alíquotas ICMS'!$E5,,MATCH(I5,'Alíquotas ICMS'!$E5:$L5,0)-2),I$4)-I$4)*H5)/(EOMONTH(I$4,0)-I$4),4) -> 0.25 | J36: =ROUND(((EOMONTH(J$4,0)-MAX(OFFSET('Alíquotas ICMS'!$E5,,MATCH(J5,'Alíquotas ICMS'!$E5:$L5,0)-2),J$4))*J5+(MAX(OFFSET('Alíquotas ICMS'!$E5,,MATCH(J5,'Alíquotas ICMS'!$E5:$L5,0)-2),J$4)-J$4)*I5)/(EOMONTH(J$4,0)-J$4),4) -> 0.186 | K36: =ROUND(((EOMONTH(K$4,0)-MAX(OFFSET('Alíquotas ICMS'!$E5,,MATCH(K5,'Alíquotas ICMS'!$E5:$L5,0)-2),K$4))*K5+(MAX(OFFSET('Alíquotas ICMS'!$E5,,MATCH(K5,'Alíquotas ICMS'!$E5:$L5,0)-2),K$4)-K$4)*J5)/(EOMONTH(K$4,0)-K$4),4) -> 0.17 | ... O36: =ROUND(((EOMONTH(O$4,0)-MAX(OFFSET('Alíquotas ICMS'!$E5,,MATCH(O5,'Alíquotas ICMS'!$E5:$L5,0)-2),O$4))*O5+(MAX(OFFSET('Alíquotas ICMS'!$E5,,MATCH(O5,'Alíquotas ICMS'!$E5:$L5,0)-2),O$4)-O$4)*N5)/(EOMONTH(O$4,0)-O$4),4) -> 0.17
B37: =B6 -> AL | D37: =ROUND(((EOMONTH(D$4,0)-MAX(OFFSET('Alíquotas ICMS'!$E6,,MATCH(D6,'Alíquotas ICMS'!$E6:$L6,0)-2),D$4))*D6+(MAX(OFFSET('Alíquotas ICMS'!$E6,,MATCH(D6,'Alíquotas ICMS'!$E6:$L6,0)-2),D$4)-D$4)*C6)/(EOMONTH(D$4,0)-D$4),4) -> 0.3 | E37: =ROUND(((EOMONTH(E$4,0)-MAX(OFFSET('Alíquotas ICMS'!$E6,,MATCH(E6,'Alíquotas ICMS'!$E6:$L6,0)-2),E$4))*E6+(MAX(OFFSET('Alíquotas ICMS'!$E6,,MATCH(E6,'Alíquotas ICMS'!$E6:$L6,0)-2),E$4)-E$4)*D6)/(EOMONTH(E$4,0)-E$4),4) -> 0.3 | F37: =ROUND(((EOMONTH(F$4,0)-MAX(OFFSET('Alíquotas ICMS'!$E6,,MATCH(F6,'Alíquotas ICMS'!$E6:$L6,0)-2),F$4))*F6+(MAX(OFFSET('Alíquotas ICMS'!$E6,,MATCH(F6,'Alíquotas ICMS'!$E6:$L6,0)-2),F$4)-F$4)*E6)/(EOMONTH(F$4,0)-F$4),4) -> 0.3 | G37: =ROUND(((EOMONTH(G$4,0)-MAX(OFFSET('Alíquotas ICMS'!$E6,,MATCH(G6,'Alíquotas ICMS'!$E6:$L6,0)-2),G$4))*G6+(MAX(OFFSET('Alíquotas ICMS'!$E6,,MATCH(G6,'Alíquotas ICMS'!$E6:$L6,0)-2),G$4)-G$4)*F6)/(EOMONTH(G$4,0)-G$4),4) -> 0.3 | H37: =ROUND(((EOMONTH(H$4,0)-MAX(OFFSET('Alíquotas ICMS'!$E6,,MATCH(H6,'Alíquotas ICMS'!$E6:$L6,0)-2),H$4))*H6+(MAX(OFFSET('Alíquotas ICMS'!$E6,,MATCH(H6,'Alíquotas ICMS'!$E6:$L6,0)-2),H$4)-H$4)*G6)/(EOMONTH(H$4,0)-H$4),4) -> 0.3 | I37: =ROUND(((EOMONTH(I$4,0)-MAX(OFFSET('Alíquotas ICMS'!$E6,,MATCH(I6,'Alíquotas ICMS'!$E6:$L6,0)-2),I$4))*I6+(MAX(OFFSET('Alíquotas ICMS'!$E6,,MATCH(I6,'Alíquotas ICMS'!$E6:$L6,0)-2),I$4)-I$4)*H6)/(EOMONTH(I$4,0)-I$4),4) -> 0.3 | J37: =ROUND(((EOMONTH(J$4,0)-MAX(OFFSET('Alíquotas ICMS'!$E6,,MATCH(J6,'Alíquotas ICMS'!$E6:$L6,0)-2),J$4))*J6+(MAX(OFFSET('Alíquotas ICMS'!$E6,,MATCH(J6,'Alíquotas ICMS'!$E6:$L6,0)-2),J$4)-J$4)*I6)/(EOMONTH(J$4,0)-J$4),4) -> 0.212 | K37: =ROUND(((EOMONTH(K$4,0)-MAX(OFFSET('Alíquotas ICMS'!$E6,,MATCH(K6,'Alíquotas ICMS'!$E6:$L6,0)-2),K$4))*K6+(MAX(OFFSET('Alíquotas ICMS'!$E6,,MATCH(K6,'Alíquotas ICMS'!$E6:$L6,0)-2),K$4)-K$4)*J6)/(EOMONTH(K$4,0)-K$4),4) -> 0.19 | ... O37: =ROUND(((EOMONTH(O$4,0)-MAX(OFFSET('Alíquotas ICMS'!$E6,,MATCH(O6,'Alíquotas ICMS'!$E6:$L6,0)-2),O$4))*O6+(MAX(OFFSET('Alíquotas ICMS'!$E6,,MATCH(O6,'Alíquotas ICMS'!$E6:$L6,0)-2),O$4)-O$4)*N6)/(EOMONTH(O$4,0)-O$4),4) -> 0.19
B38: =B7 -> AM | D38: =ROUND(((EOMONTH(D$4,0)-MAX(OFFSET('Alíquotas ICMS'!$E7,,MATCH(D7,'Alíquotas ICMS'!$E7:$L7,0)-2),D$4))*D7+(MAX(OFFSET('Alíquotas ICMS'!$E7,,MATCH(D7,'Alíquotas ICMS'!$E7:$L7,0)-2),D$4)-D$4)*C7)/(EOMONTH(D$4,0)-D$4),4) -> 0.3 | E38: =ROUND(((EOMONTH(E$4,0)-MAX(OFFSET('Alíquotas ICMS'!$E7,,MATCH(E7,'Alíquotas ICMS'!$E7:$L7,0)-2),E$4))*E7+(MAX(OFFSET('Alíquotas ICMS'!$E7,,MATCH(E7,'Alíquotas ICMS'!$E7:$L7,0)-2),E$4)-E$4)*D7)/(EOMONTH(E$4,0)-E$4),4) -> 0.3 | F38: =ROUND(((EOMONTH(F$4,0)-MAX(OFFSET('Alíquotas ICMS'!$E7,,MATCH(F7,'Alíquotas ICMS'!$E7:$L7,0)-2),F$4))*F7+(MAX(OFFSET('Alíquotas ICMS'!$E7,,MATCH(F7,'Alíquotas ICMS'!$E7:$L7,0)-2),F$4)-F$4)*E7)/(EOMONTH(F$4,0)-F$4),4) -> 0.3 | G38: =ROUND(((EOMONTH(G$4,0)-MAX(OFFSET('Alíquotas ICMS'!$E7,,MATCH(G7,'Alíquotas ICMS'!$E7:$L7,0)-2),G$4))*G7+(MAX(OFFSET('Alíquotas ICMS'!$E7,,MATCH(G7,'Alíquotas ICMS'!$E7:$L7,0)-2),G$4)-G$4)*F7)/(EOMONTH(G$4,0)-G$4),4) -> 0.3 | H38: =ROUND(((EOMONTH(H$4,0)-MAX(OFFSET('Alíquotas ICMS'!$E7,,MATCH(H7,'Alíquotas ICMS'!$E7:$L7,0)-2),H$4))*H7+(MAX(OFFSET('Alíquotas ICMS'!$E7,,MATCH(H7,'Alíquotas ICMS'!$E7:$L7,0)-2),H$4)-H$4)*G7)/(EOMONTH(H$4,0)-H$4),4) -> 0.3 | I38: =ROUND(((EOMONTH(I$4,0)-MAX(OFFSET('Alíquotas ICMS'!$E7,,MATCH(I7,'Alíquotas ICMS'!$E7:$L7,0)-2),I$4))*I7+(MAX(OFFSET('Alíquotas ICMS'!$E7,,MATCH(I7,'Alíquotas ICMS'!$E7:$L7,0)-2),I$4)-I$4)*H7)/(EOMONTH(I$4,0)-I$4),4) -> 0.3 | J38: =ROUND(((EOMONTH(J$4,0)-MAX(OFFSET('Alíquotas ICMS'!$E7,,MATCH(J7,'Alíquotas ICMS'!$E7:$L7,0)-2),J$4))*J7+(MAX(OFFSET('Alíquotas ICMS'!$E7,,MATCH(J7,'Alíquotas ICMS'!$E7:$L7,0)-2),J$4)-J$4)*I7)/(EOMONTH(J$4,0)-J$4),4) -> 0.18 | K38: =ROUND(((EOMONTH(K$4,0)-MAX(OFFSET('Alíquotas ICMS'!$E7,,MATCH(K7,'Alíquotas ICMS'!$E7:$L7,0)-2),K$4))*K7+(MAX(OFFSET('Alíquotas ICMS'!$E7,,MATCH(K7,'Alíquotas ICMS'!$E7:$L7,0)-2),K$4)-K$4)*J7)/(EOMONTH(K$4,0)-K$4),4) -> 0.18 | ... O38: =ROUND(((EOMONTH(O$4,0)-MAX(OFFSET('Alíquotas ICMS'!$E7,,MATCH(O7,'Alíquotas ICMS'!$E7:$L7,0)-2),O$4))*O7+(MAX(OFFSET('Alíquotas ICMS'!$E7,,MATCH(O7,'Alíquotas ICMS'!$E7:$L7,0)-2),O$4)-O$4)*N7)/(EOMONTH(O$4,0)-O$4),4) -> 0.18
B39: =B8 -> AP | D39: =ROUND(((EOMONTH(D$4,0)-MAX(OFFSET('Alíquotas ICMS'!$E8,,MATCH(D8,'Alíquotas ICMS'!$E8:$L8,0)-2),D$4))*D8+(MAX(OFFSET('Alíquotas ICMS'!$E8,,MATCH(D8,'Alíquotas ICMS'!$E8:$L8,0)-2),D$4)-D$4)*C8)/(EOMONTH(D$4,0)-D$4),4) -> 0.29 | E39: =ROUND(((EOMONTH(E$4,0)-MAX(OFFSET('Alíquotas ICMS'!$E8,,MATCH(E8,'Alíquotas ICMS'!$E8:$L8,0)-2),E$4))*E8+(MAX(OFFSET('Alíquotas ICMS'!$E8,,MATCH(E8,'Alíquotas ICMS'!$E8:$L8,0)-2),E$4)-E$4)*D8)/(EOMONTH(E$4,0)-E$4),4) -> 0.29 | F39: =ROUND(((EOMONTH(F$4,0)-MAX(OFFSET('Alíquotas ICMS'!$E8,,MATCH(F8,'Alíquotas ICMS'!$E8:$L8,0)-2),F$4))*F8+(MAX(OFFSET('Alíquotas ICMS'!$E8,,MATCH(F8,'Alíquotas ICMS'!$E8:$L8,0)-2),F$4)-F$4)*E8)/(EOMONTH(F$4,0)-F$4),4) -> 0.29 | G39: =ROUND(((EOMONTH(G$4,0)-MAX(OFFSET('Alíquotas ICMS'!$E8,,MATCH(G8,'Alíquotas ICMS'!$E8:$L8,0)-2),G$4))*G8+(MAX(OFFSET('Alíquotas ICMS'!$E8,,MATCH(G8,'Alíquotas ICMS'!$E8:$L8,0)-2),G$4)-G$4)*F8)/(EOMONTH(G$4,0)-G$4),4) -> 0.29 | H39: =ROUND(((EOMONTH(H$4,0)-MAX(OFFSET('Alíquotas ICMS'!$E8,,MATCH(H8,'Alíquotas ICMS'!$E8:$L8,0)-2),H$4))*H8+(MAX(OFFSET('Alíquotas ICMS'!$E8,,MATCH(H8,'Alíquotas ICMS'!$E8:$L8,0)-2),H$4)-H$4)*G8)/(EOMONTH(H$4,0)-H$4),4) -> 0.29 | I39: =ROUND(((EOMONTH(I$4,0)-MAX(OFFSET('Alíquotas ICMS'!$E8,,MATCH(I8,'Alíquotas ICMS'!$E8:$L8,0)-2),I$4))*I8+(MAX(OFFSET('Alíquotas ICMS'!$E8,,MATCH(I8,'Alíquotas ICMS'!$E8:$L8,0)-2),I$4)-I$4)*H8)/(EOMONTH(I$4,0)-I$4),4) -> 0.29 | J39: =ROUND(((EOMONTH(J$4,0)-MAX(OFFSET('Alíquotas ICMS'!$E8,,MATCH(J8,'Alíquotas ICMS'!$E8:$L8,0)-2),J$4))*J8+(MAX(OFFSET('Alíquotas ICMS'!$E8,,MATCH(J8,'Alíquotas ICMS'!$E8:$L8,0)-2),J$4)-J$4)*I8)/(EOMONTH(J$4,0)-J$4),4) -> 0.29 | K39: =ROUND(((EOMONTH(K$4,0)-MAX(OFFSET('Alíquotas ICMS'!$E8,,MATCH(K8,'Alíquotas ICMS'!$E8:$L8,0)-2),K$4))*K8+(MAX(OFFSET('Alíquotas ICMS'!$E8,,MATCH(K8,'Alíquotas ICMS'!$E8:$L8,0)-2),K$4)-K$4)*J8)/(EOMONTH(K$4,0)-K$4),4) -> 0.29 | ... O39: =ROUND(((EOMONTH(O$4,0)-MAX(OFFSET('Alíquotas ICMS'!$E8,,MATCH(O8,'Alíquotas ICMS'!$E8:$L8,0)-2),O$4))*O8+(MAX(OFFSET('Alíquotas ICMS'!$E8,,MATCH(O8,'Alíquotas ICMS'!$E8:$L8,0)-2),O$4)-O$4)*N8)/(EOMONTH(O$4,0)-O$4),4) -> 0.29
B40: =B9 -> BA | D40: =ROUND(((EOMONTH(D$4,0)-MAX(OFFSET('Alíquotas ICMS'!$E9,,MATCH(D9,'Alíquotas ICMS'!$E9:$L9,0)-2),D$4))*D9+(MAX(OFFSET('Alíquotas ICMS'!$E9,,MATCH(D9,'Alíquotas ICMS'!$E9:$L9,0)-2),D$4)-D$4)*C9)/(EOMONTH(D$4,0)-D$4),4) -> 0.28 | E40: =ROUND(((EOMONTH(E$4,0)-MAX(OFFSET('Alíquotas ICMS'!$E9,,MATCH(E9,'Alíquotas ICMS'!$E9:$L9,0)-2),E$4))*E9+(MAX(OFFSET('Alíquotas ICMS'!$E9,,MATCH(E9,'Alíquotas ICMS'!$E9:$L9,0)-2),E$4)-E$4)*D9)/(EOMONTH(E$4,0)-E$4),4) -> 0.28 | F40: =ROUND(((EOMONTH(F$4,0)-MAX(OFFSET('Alíquotas ICMS'!$E9,,MATCH(F9,'Alíquotas ICMS'!$E9:$L9,0)-2),F$4))*F9+(MAX(OFFSET('Alíquotas ICMS'!$E9,,MATCH(F9,'Alíquotas ICMS'!$E9:$L9,0)-2),F$4)-F$4)*E9)/(EOMONTH(F$4,0)-F$4),4) -> 0.28 | G40: =ROUND(((EOMONTH(G$4,0)-MAX(OFFSET('Alíquotas ICMS'!$E9,,MATCH(G9,'Alíquotas ICMS'!$E9:$L9,0)-2),G$4))*G9+(MAX(OFFSET('Alíquotas ICMS'!$E9,,MATCH(G9,'Alíquotas ICMS'!$E9:$L9,0)-2),G$4)-G$4)*F9)/(EOMONTH(G$4,0)-G$4),4) -> 0.28 | H40: =ROUND(((EOMONTH(H$4,0)-MAX(OFFSET('Alíquotas ICMS'!$E9,,MATCH(H9,'Alíquotas ICMS'!$E9:$L9,0)-2),H$4))*H9+(MAX(OFFSET('Alíquotas ICMS'!$E9,,MATCH(H9,'Alíquotas ICMS'!$E9:$L9,0)-2),H$4)-H$4)*G9)/(EOMONTH(H$4,0)-H$4),4) -> 0.28 | I40: =ROUND(((EOMONTH(I$4,0)-MAX(OFFSET('Alíquotas ICMS'!$E9,,MATCH(I9,'Alíquotas ICMS'!$E9:$L9,0)-2),I$4))*I9+(MAX(OFFSET('Alíquotas ICMS'!$E9,,MATCH(I9,'Alíquotas ICMS'!$E9:$L9,0)-2),I$4)-I$4)*H9)/(EOMONTH(I$4,0)-I$4),4) -> 0.2559 | J40: =ROUND(((EOMONTH(J$4,0)-MAX(OFFSET('Alíquotas ICMS'!$E9,,MATCH(J9,'Alíquotas ICMS'!$E9:$L9,0)-2),J$4))*J9+(MAX(OFFSET('Alíquotas ICMS'!$E9,,MATCH(J9,'Alíquotas ICMS'!$E9:$L9,0)-2),J$4)-J$4)*I9)/(EOMONTH(J$4,0)-J$4),4) -> 0.18 | K40: =ROUND(((EOMONTH(K$4,0)-MAX(OFFSET('Alíquotas ICMS'!$E9,,MATCH(K9,'Alíquotas ICMS'!$E9:$L9,0)-2),K$4))*K9+(MAX(OFFSET('Alíquotas ICMS'!$E9,,MATCH(K9,'Alíquotas ICMS'!$E9:$L9,0)-2),K$4)-K$4)*J9)/(EOMONTH(K$4,0)-K$4),4) -> 0.18 | ... O40: =ROUND(((EOMONTH(O$4,0)-MAX(OFFSET('Alíquotas ICMS'!$E9,,MATCH(O9,'Alíquotas ICMS'!$E9:$L9,0)-2),O$4))*O9+(MAX(OFFSET('Alíquotas ICMS'!$E9,,MATCH(O9,'Alíquotas ICMS'!$E9:$L9,0)-2),O$4)-O$4)*N9)/(EOMONTH(O$4,0)-O$4),4) -> 0.18
B41: =B10 -> CE | D41: =ROUND(((EOMONTH(D$4,0)-MAX(OFFSET('Alíquotas ICMS'!$E10,,MATCH(D10,'Alíquotas ICMS'!$E10:$L10,0)-2),D$4))*D10+(MAX(OFFSET('Alíquotas ICMS'!$E10,,MATCH(D10,'Alíquotas ICMS'!$E10:$L10,0)-2),D$4)-D$4)*C10)/(EOMONTH(D$4,0)-D$4),4) -> 0.3 | E41: =ROUND(((EOMONTH(E$4,0)-MAX(OFFSET('Alíquotas ICMS'!$E10,,MATCH(E10,'Alíquotas ICMS'!$E10:$L10,0)-2),E$4))*E10+(MAX(OFFSET('Alíquotas ICMS'!$E10,,MATCH(E10,'Alíquotas ICMS'!$E10:$L10,0)-2),E$4)-E$4)*D10)/(EOMONTH(E$4,0)-E$4),4) -> 0.3 | F41: =ROUND(((EOMONTH(F$4,0)-MAX(OFFSET('Alíquotas ICMS'!$E10,,MATCH(F10,'Alíquotas ICMS'!$E10:$L10,0)-2),F$4))*F10+(MAX(OFFSET('Alíquotas ICMS'!$E10,,MATCH(F10,'Alíquotas ICMS'!$E10:$L10,0)-2),F$4)-F$4)*E10)/(EOMONTH(F$4,0)-F$4),4) -> 0.3 | G41: =ROUND(((EOMONTH(G$4,0)-MAX(OFFSET('Alíquotas ICMS'!$E10,,MATCH(G10,'Alíquotas ICMS'!$E10:$L10,0)-2),G$4))*G10+(MAX(OFFSET('Alíquotas ICMS'!$E10,,MATCH(G10,'Alíquotas ICMS'!$E10:$L10,0)-2),G$4)-G$4)*F10)/(EOMONTH(G$4,0)-G$4),4) -> 0.3 | H41: =ROUND(((EOMONTH(H$4,0)-MAX(OFFSET('Alíquotas ICMS'!$E10,,MATCH(H10,'Alíquotas ICMS'!$E10:$L10,0)-2),H$4))*H10+(MAX(OFFSET('Alíquotas ICMS'!$E10,,MATCH(H10,'Alíquotas ICMS'!$E10:$L10,0)-2),H$4)-H$4)*G10)/(EOMONTH(H$4,0)-H$4),4) -> 0.3 | I41: =ROUND(((EOMONTH(I$4,0)-MAX(OFFSET('Alíquotas ICMS'!$E10,,MATCH(I10,'Alíquotas ICMS'!$E10:$L10,0)-2),I$4))*I10+(MAX(OFFSET('Alíquotas ICMS'!$E10,,MATCH(I10,'Alíquotas ICMS'!$E10:$L10,0)-2),I$4)-I$4)*H10)/(EOMONTH(I$4,0)-I$4),4) -> 0.3 | J41: =ROUND(((EOMONTH(J$4,0)-MAX(OFFSET('Alíquotas ICMS'!$E10,,MATCH(J10,'Alíquotas ICMS'!$E10:$L10,0)-2),J$4))*J10+(MAX(OFFSET('Alíquotas ICMS'!$E10,,MATCH(J10,'Alíquotas ICMS'!$E10:$L10,0)-2),J$4)-J$4)*I10)/(EOMONTH(J$4,0)-J$4),4) -> 0.224 | K41: =ROUND(((EOMONTH(K$4,0)-MAX(OFFSET('Alíquotas ICMS'!$E10,,MATCH(K10,'Alíquotas ICMS'!$E10:$L10,0)-2),K$4))*K10+(MAX(OFFSET('Alíquotas ICMS'!$E10,,MATCH(K10,'Alíquotas ICMS'!$E10:$L10,0)-2),K$4)-K$4)*J10)/(EOMONTH(K$4,0)-K$4),4) -> 0.18 | ... O41: =ROUND(((EOMONTH(O$4,0)-MAX(OFFSET('Alíquotas ICMS'!$E10,,MATCH(O10,'Alíquotas ICMS'!$E10:$L10,0)-2),O$4))*O10+(MAX(OFFSET('Alíquotas ICMS'!$E10,,MATCH(O10,'Alíquotas ICMS'!$E10:$L10,0)-2),O$4)-O$4)*N10)/(EOMONTH(O$4,0)-O$4),4) -> 0.18
B42: =B11 -> DF | D42: =ROUND(((EOMONTH(D$4,0)-MAX(OFFSET('Alíquotas ICMS'!$E11,,MATCH(D11,'Alíquotas ICMS'!$E11:$L11,0)-2),D$4))*D11+(MAX(OFFSET('Alíquotas ICMS'!$E11,,MATCH(D11,'Alíquotas ICMS'!$E11:$L11,0)-2),D$4)-D$4)*C11)/(EOMONTH(D$4,0)-D$4),4) -> 0.28 | E42: =ROUND(((EOMONTH(E$4,0)-MAX(OFFSET('Alíquotas ICMS'!$E11,,MATCH(E11,'Alíquotas ICMS'!$E11:$L11,0)-2),E$4))*E11+(MAX(OFFSET('Alíquotas ICMS'!$E11,,MATCH(E11,'Alíquotas ICMS'!$E11:$L11,0)-2),E$4)-E$4)*D11)/(EOMONTH(E$4,0)-E$4),4) -> 0.28 | F42: =ROUND(((EOMONTH(F$4,0)-MAX(OFFSET('Alíquotas ICMS'!$E11,,MATCH(F11,'Alíquotas ICMS'!$E11:$L11,0)-2),F$4))*F11+(MAX(OFFSET('Alíquotas ICMS'!$E11,,MATCH(F11,'Alíquotas ICMS'!$E11:$L11,0)-2),F$4)-F$4)*E11)/(EOMONTH(F$4,0)-F$4),4) -> 0.28 | G42: =ROUND(((EOMONTH(G$4,0)-MAX(OFFSET('Alíquotas ICMS'!$E11,,MATCH(G11,'Alíquotas ICMS'!$E11:$L11,0)-2),G$4))*G11+(MAX(OFFSET('Alíquotas ICMS'!$E11,,MATCH(G11,'Alíquotas ICMS'!$E11:$L11,0)-2),G$4)-G$4)*F11)/(EOMONTH(G$4,0)-G$4),4) -> 0.28 | H42: =ROUND(((EOMONTH(H$4,0)-MAX(OFFSET('Alíquotas ICMS'!$E11,,MATCH(H11,'Alíquotas ICMS'!$E11:$L11,0)-2),H$4))*H11+(MAX(OFFSET('Alíquotas ICMS'!$E11,,MATCH(H11,'Alíquotas ICMS'!$E11:$L11,0)-2),H$4)-H$4)*G11)/(EOMONTH(H$4,0)-H$4),4) -> 0.28 | I42: =ROUND(((EOMONTH(I$4,0)-MAX(OFFSET('Alíquotas ICMS'!$E11,,MATCH(I11,'Alíquotas ICMS'!$E11:$L11,0)-2),I$4))*I11+(MAX(OFFSET('Alíquotas ICMS'!$E11,,MATCH(I11,'Alíquotas ICMS'!$E11:$L11,0)-2),I$4)-I$4)*H11)/(EOMONTH(I$4,0)-I$4),4) -> 0.2559 | J42: =ROUND(((EOMONTH(J$4,0)-MAX(OFFSET('Alíquotas ICMS'!$E11,,MATCH(J11,'Alíquotas ICMS'!$E11:$L11,0)-2),J$4))*J11+(MAX(OFFSET('Alíquotas ICMS'!$E11,,MATCH(J11,'Alíquotas ICMS'!$E11:$L11,0)-2),J$4)-J$4)*I11)/(EOMONTH(J$4,0)-J$4),4) -> 0.18 | K42: =ROUND(((EOMONTH(K$4,0)-MAX(OFFSET('Alíquotas ICMS'!$E11,,MATCH(K11,'Alíquotas ICMS'!$E11:$L11,0)-2),K$4))*K11+(MAX(OFFSET('Alíquotas ICMS'!$E11,,MATCH(K11,'Alíquotas ICMS'!$E11:$L11,0)-2),K$4)-K$4)*J11)/(EOMONTH(K$4,0)-K$4),4) -> 0.18 | ... O42: =ROUND(((EOMONTH(O$4,0)-MAX(OFFSET('Alíquotas ICMS'!$E11,,MATCH(O11,'Alíquotas ICMS'!$E11:$L11,0)-2),O$4))*O11+(MAX(OFFSET('Alíquotas ICMS'!$E11,,MATCH(O11,'Alíquotas ICMS'!$E11:$L11,0)-2),O$4)-O$4)*N11)/(EOMONTH(O$4,0)-O$4),4) -> 0.18
B43: =B12 -> ES | D43: =ROUND(((EOMONTH(D$4,0)-MAX(OFFSET('Alíquotas ICMS'!$E12,,MATCH(D12,'Alíquotas ICMS'!$E12:$L12,0)-2),D$4))*D12+(MAX(OFFSET('Alíquotas ICMS'!$E12,,MATCH(D12,'Alíquotas ICMS'!$E12:$L12,0)-2),D$4)-D$4)*C12)/(EOMONTH(D$4,0)-D$4),4) -> 0.25 | E43: =ROUND(((EOMONTH(E$4,0)-MAX(OFFSET('Alíquotas ICMS'!$E12,,MATCH(E12,'Alíquotas ICMS'!$E12:$L12,0)-2),E$4))*E12+(MAX(OFFSET('Alíquotas ICMS'!$E12,,MATCH(E12,'Alíquotas ICMS'!$E12:$L12,0)-2),E$4)-E$4)*D12)/(EOMONTH(E$4,0)-E$4),4) -> 0.25 | F43: =ROUND(((EOMONTH(F$4,0)-MAX(OFFSET('Alíquotas ICMS'!$E12,,MATCH(F12,'Alíquotas ICMS'!$E12:$L12,0)-2),F$4))*F12+(MAX(OFFSET('Alíquotas ICMS'!$E12,,MATCH(F12,'Alíquotas ICMS'!$E12:$L12,0)-2),F$4)-F$4)*E12)/(EOMONTH(F$4,0)-F$4),4) -> 0.25 | G43: =ROUND(((EOMONTH(G$4,0)-MAX(OFFSET('Alíquotas ICMS'!$E12,,MATCH(G12,'Alíquotas ICMS'!$E12:$L12,0)-2),G$4))*G12+(MAX(OFFSET('Alíquotas ICMS'!$E12,,MATCH(G12,'Alíquotas ICMS'!$E12:$L12,0)-2),G$4)-G$4)*F12)/(EOMONTH(G$4,0)-G$4),4) -> 0.25 | H43: =ROUND(((EOMONTH(H$4,0)-MAX(OFFSET('Alíquotas ICMS'!$E12,,MATCH(H12,'Alíquotas ICMS'!$E12:$L12,0)-2),H$4))*H12+(MAX(OFFSET('Alíquotas ICMS'!$E12,,MATCH(H12,'Alíquotas ICMS'!$E12:$L12,0)-2),H$4)-H$4)*G12)/(EOMONTH(H$4,0)-H$4),4) -> 0.25 | I43: =ROUND(((EOMONTH(I$4,0)-MAX(OFFSET('Alíquotas ICMS'!$E12,,MATCH(I12,'Alíquotas ICMS'!$E12:$L12,0)-2),I$4))*I12+(MAX(OFFSET('Alíquotas ICMS'!$E12,,MATCH(I12,'Alíquotas ICMS'!$E12:$L12,0)-2),I$4)-I$4)*H12)/(EOMONTH(I$4,0)-I$4),4) -> 0.25 | J43: =ROUND(((EOMONTH(J$4,0)-MAX(OFFSET('Alíquotas ICMS'!$E12,,MATCH(J12,'Alíquotas ICMS'!$E12:$L12,0)-2),J$4))*J12+(MAX(OFFSET('Alíquotas ICMS'!$E12,,MATCH(J12,'Alíquotas ICMS'!$E12:$L12,0)-2),J$4)-J$4)*I12)/(EOMONTH(J$4,0)-J$4),4) -> 0.17 | K43: =ROUND(((EOMONTH(K$4,0)-MAX(OFFSET('Alíquotas ICMS'!$E12,,MATCH(K12,'Alíquotas ICMS'!$E12:$L12,0)-2),K$4))*K12+(MAX(OFFSET('Alíquotas ICMS'!$E12,,MATCH(K12,'Alíquotas ICMS'!$E12:$L12,0)-2),K$4)-K$4)*J12)/(EOMONTH(K$4,0)-K$4),4) -> 0.17 | ... O43: =ROUND(((EOMONTH(O$4,0)-MAX(OFFSET('Alíquotas ICMS'!$E12,,MATCH(O12,'Alíquotas ICMS'!$E12:$L12,0)-2),O$4))*O12+(MAX(OFFSET('Alíquotas ICMS'!$E12,,MATCH(O12,'Alíquotas ICMS'!$E12:$L12,0)-2),O$4)-O$4)*N12)/(EOMONTH(O$4,0)-O$4),4) -> 0.17
B44: =B13 -> GO | D44: =ROUND(((EOMONTH(D$4,0)-MAX(OFFSET('Alíquotas ICMS'!$E13,,MATCH(D13,'Alíquotas ICMS'!$E13:$L13,0)-2),D$4))*D13+(MAX(OFFSET('Alíquotas ICMS'!$E13,,MATCH(D13,'Alíquotas ICMS'!$E13:$L13,0)-2),D$4)-D$4)*C13)/(EOMONTH(D$4,0)-D$4),4) -> 0.29 | E44: =ROUND(((EOMONTH(E$4,0)-MAX(OFFSET('Alíquotas ICMS'!$E13,,MATCH(E13,'Alíquotas ICMS'!$E13:$L13,0)-2),E$4))*E13+(MAX(OFFSET('Alíquotas ICMS'!$E13,,MATCH(E13,'Alíquotas ICMS'!$E13:$L13,0)-2),E$4)-E$4)*D13)/(EOMONTH(E$4,0)-E$4),4) -> 0.29 | F44: =ROUND(((EOMONTH(F$4,0)-MAX(OFFSET('Alíquotas ICMS'!$E13,,MATCH(F13,'Alíquotas ICMS'!$E13:$L13,0)-2),F$4))*F13+(MAX(OFFSET('Alíquotas ICMS'!$E13,,MATCH(F13,'Alíquotas ICMS'!$E13:$L13,0)-2),F$4)-F$4)*E13)/(EOMONTH(F$4,0)-F$4),4) -> 0.29 | G44: =ROUND(((EOMONTH(G$4,0)-MAX(OFFSET('Alíquotas ICMS'!$E13,,MATCH(G13,'Alíquotas ICMS'!$E13:$L13,0)-2),G$4))*G13+(MAX(OFFSET('Alíquotas ICMS'!$E13,,MATCH(G13,'Alíquotas ICMS'!$E13:$L13,0)-2),G$4)-G$4)*F13)/(EOMONTH(G$4,0)-G$4),4) -> 0.29 | H44: =ROUND(((EOMONTH(H$4,0)-MAX(OFFSET('Alíquotas ICMS'!$E13,,MATCH(H13,'Alíquotas ICMS'!$E13:$L13,0)-2),H$4))*H13+(MAX(OFFSET('Alíquotas ICMS'!$E13,,MATCH(H13,'Alíquotas ICMS'!$E13:$L13,0)-2),H$4)-H$4)*G13)/(EOMONTH(H$4,0)-H$4),4) -> 0.29 | I44: =ROUND(((EOMONTH(I$4,0)-MAX(OFFSET('Alíquotas ICMS'!$E13,,MATCH(I13,'Alíquotas ICMS'!$E13:$L13,0)-2),I$4))*I13+(MAX(OFFSET('Alíquotas ICMS'!$E13,,MATCH(I13,'Alíquotas ICMS'!$E13:$L13,0)-2),I$4)-I$4)*H13)/(EOMONTH(I$4,0)-I$4),4) -> 0.261 | J44: =ROUND(((EOMONTH(J$4,0)-MAX(OFFSET('Alíquotas ICMS'!$E13,,MATCH(J13,'Alíquotas ICMS'!$E13:$L13,0)-2),J$4))*J13+(MAX(OFFSET('Alíquotas ICMS'!$E13,,MATCH(J13,'Alíquotas ICMS'!$E13:$L13,0)-2),J$4)-J$4)*I13)/(EOMONTH(J$4,0)-J$4),4) -> 0.17 | K44: =ROUND(((EOMONTH(K$4,0)-MAX(OFFSET('Alíquotas ICMS'!$E13,,MATCH(K13,'Alíquotas ICMS'!$E13:$L13,0)-2),K$4))*K13+(MAX(OFFSET('Alíquotas ICMS'!$E13,,MATCH(K13,'Alíquotas ICMS'!$E13:$L13,0)-2),K$4)-K$4)*J13)/(EOMONTH(K$4,0)-K$4),4) -> 0.17 | ... O44: =ROUND(((EOMONTH(O$4,0)-MAX(OFFSET('Alíquotas ICMS'!$E13,,MATCH(O13,'Alíquotas ICMS'!$E13:$L13,0)-2),O$4))*O13+(MAX(OFFSET('Alíquotas ICMS'!$E13,,MATCH(O13,'Alíquotas ICMS'!$E13:$L13,0)-2),O$4)-O$4)*N13)/(EOMONTH(O$4,0)-O$4),4) -> 0.17
B45: =B14 -> MA | D45: =ROUND(((EOMONTH(D$4,0)-MAX(OFFSET('Alíquotas ICMS'!$E14,,MATCH(D14,'Alíquotas ICMS'!$E14:$L14,0)-2),D$4))*D14+(MAX(OFFSET('Alíquotas ICMS'!$E14,,MATCH(D14,'Alíquotas ICMS'!$E14:$L14,0)-2),D$4)-D$4)*C14)/(EOMONTH(D$4,0)-D$4),4) -> 0.29 | E45: =ROUND(((EOMONTH(E$4,0)-MAX(OFFSET('Alíquotas ICMS'!$E14,,MATCH(E14,'Alíquotas ICMS'!$E14:$L14,0)-2),E$4))*E14+(MAX(OFFSET('Alíquotas ICMS'!$E14,,MATCH(E14,'Alíquotas ICMS'!$E14:$L14,0)-2),E$4)-E$4)*D14)/(EOMONTH(E$4,0)-E$4),4) -> 0.29 | F45: =ROUND(((EOMONTH(F$4,0)-MAX(OFFSET('Alíquotas ICMS'!$E14,,MATCH(F14,'Alíquotas ICMS'!$E14:$L14,0)-2),F$4))*F14+(MAX(OFFSET('Alíquotas ICMS'!$E14,,MATCH(F14,'Alíquotas ICMS'!$E14:$L14,0)-2),F$4)-F$4)*E14)/(EOMONTH(F$4,0)-F$4),4) -> 0.29 | G45: =ROUND(((EOMONTH(G$4,0)-MAX(OFFSET('Alíquotas ICMS'!$E14,,MATCH(G14,'Alíquotas ICMS'!$E14:$L14,0)-2),G$4))*G14+(MAX(OFFSET('Alíquotas ICMS'!$E14,,MATCH(G14,'Alíquotas ICMS'!$E14:$L14,0)-2),G$4)-G$4)*F14)/(EOMONTH(G$4,0)-G$4),4) -> 0.29 | H45: =ROUND(((EOMONTH(H$4,0)-MAX(OFFSET('Alíquotas ICMS'!$E14,,MATCH(H14,'Alíquotas ICMS'!$E14:$L14,0)-2),H$4))*H14+(MAX(OFFSET('Alíquotas ICMS'!$E14,,MATCH(H14,'Alíquotas ICMS'!$E14:$L14,0)-2),H$4)-H$4)*G14)/(EOMONTH(H$4,0)-H$4),4) -> 0.29 | I45: =ROUND(((EOMONTH(I$4,0)-MAX(OFFSET('Alíquotas ICMS'!$E14,,MATCH(I14,'Alíquotas ICMS'!$E14:$L14,0)-2),I$4))*I14+(MAX(OFFSET('Alíquotas ICMS'!$E14,,MATCH(I14,'Alíquotas ICMS'!$E14:$L14,0)-2),I$4)-I$4)*H14)/(EOMONTH(I$4,0)-I$4),4) -> 0.29 | J45: =ROUND(((EOMONTH(J$4,0)-MAX(OFFSET('Alíquotas ICMS'!$E14,,MATCH(J14,'Alíquotas ICMS'!$E14:$L14,0)-2),J$4))*J14+(MAX(OFFSET('Alíquotas ICMS'!$E14,,MATCH(J14,'Alíquotas ICMS'!$E14:$L14,0)-2),J$4)-J$4)*I14)/(EOMONTH(J$4,0)-J$4),4) -> 0.224 | K45: =ROUND(((EOMONTH(K$4,0)-MAX(OFFSET('Alíquotas ICMS'!$E14,,MATCH(K14,'Alíquotas ICMS'!$E14:$L14,0)-2),K$4))*K14+(MAX(OFFSET('Alíquotas ICMS'!$E14,,MATCH(K14,'Alíquotas ICMS'!$E14:$L14,0)-2),K$4)-K$4)*J14)/(EOMONTH(K$4,0)-K$4),4) -> 0.18 | ... O45: =ROUND(((EOMONTH(O$4,0)-MAX(OFFSET('Alíquotas ICMS'!$E14,,MATCH(O14,'Alíquotas ICMS'!$E14:$L14,0)-2),O$4))*O14+(MAX(OFFSET('Alíquotas ICMS'!$E14,,MATCH(O14,'Alíquotas ICMS'!$E14:$L14,0)-2),O$4)-O$4)*N14)/(EOMONTH(O$4,0)-O$4),4) -> 0.18
B46: =B15 -> MG | D46: =ROUND(((EOMONTH(D$4,0)-MAX(OFFSET('Alíquotas ICMS'!$E15,,MATCH(D15,'Alíquotas ICMS'!$E15:$L15,0)-2),D$4))*D15+(MAX(OFFSET('Alíquotas ICMS'!$E15,,MATCH(D15,'Alíquotas ICMS'!$E15:$L15,0)-2),D$4)-D$4)*C15)/(EOMONTH(D$4,0)-D$4),4) -> 0.27 | E46: =ROUND(((EOMONTH(E$4,0)-MAX(OFFSET('Alíquotas ICMS'!$E15,,MATCH(E15,'Alíquotas ICMS'!$E15:$L15,0)-2),E$4))*E15+(MAX(OFFSET('Alíquotas ICMS'!$E15,,MATCH(E15,'Alíquotas ICMS'!$E15:$L15,0)-2),E$4)-E$4)*D15)/(EOMONTH(E$4,0)-E$4),4) -> 0.27 | F46: =ROUND(((EOMONTH(F$4,0)-MAX(OFFSET('Alíquotas ICMS'!$E15,,MATCH(F15,'Alíquotas ICMS'!$E15:$L15,0)-2),F$4))*F15+(MAX(OFFSET('Alíquotas ICMS'!$E15,,MATCH(F15,'Alíquotas ICMS'!$E15:$L15,0)-2),F$4)-F$4)*E15)/(EOMONTH(F$4,0)-F$4),4) -> 0.27 | G46: =ROUND(((EOMONTH(G$4,0)-MAX(OFFSET('Alíquotas ICMS'!$E15,,MATCH(G15,'Alíquotas ICMS'!$E15:$L15,0)-2),G$4))*G15+(MAX(OFFSET('Alíquotas ICMS'!$E15,,MATCH(G15,'Alíquotas ICMS'!$E15:$L15,0)-2),G$4)-G$4)*F15)/(EOMONTH(G$4,0)-G$4),4) -> 0.27 | H46: =ROUND(((EOMONTH(H$4,0)-MAX(OFFSET('Alíquotas ICMS'!$E15,,MATCH(H15,'Alíquotas ICMS'!$E15:$L15,0)-2),H$4))*H15+(MAX(OFFSET('Alíquotas ICMS'!$E15,,MATCH(H15,'Alíquotas ICMS'!$E15:$L15,0)-2),H$4)-H$4)*G15)/(EOMONTH(H$4,0)-H$4),4) -> 0.27 | I46: =ROUND(((EOMONTH(I$4,0)-MAX(OFFSET('Alíquotas ICMS'!$E15,,MATCH(I15,'Alíquotas ICMS'!$E15:$L15,0)-2),I$4))*I15+(MAX(OFFSET('Alíquotas ICMS'!$E15,,MATCH(I15,'Alíquotas ICMS'!$E15:$L15,0)-2),I$4)-I$4)*H15)/(EOMONTH(I$4,0)-I$4),4) -> 0.2483 | J46: =ROUND(((EOMONTH(J$4,0)-MAX(OFFSET('Alíquotas ICMS'!$E15,,MATCH(J15,'Alíquotas ICMS'!$E15:$L15,0)-2),J$4))*J15+(MAX(OFFSET('Alíquotas ICMS'!$E15,,MATCH(J15,'Alíquotas ICMS'!$E15:$L15,0)-2),J$4)-J$4)*I15)/(EOMONTH(J$4,0)-J$4),4) -> 0.18 | K46: =ROUND(((EOMONTH(K$4,0)-MAX(OFFSET('Alíquotas ICMS'!$E15,,MATCH(K15,'Alíquotas ICMS'!$E15:$L15,0)-2),K$4))*K15+(MAX(OFFSET('Alíquotas ICMS'!$E15,,MATCH(K15,'Alíquotas ICMS'!$E15:$L15,0)-2),K$4)-K$4)*J15)/(EOMONTH(K$4,0)-K$4),4) -> 0.18 | ... O46: =ROUND(((EOMONTH(O$4,0)-MAX(OFFSET('Alíquotas ICMS'!$E15,,MATCH(O15,'Alíquotas ICMS'!$E15:$L15,0)-2),O$4))*O15+(MAX(OFFSET('Alíquotas ICMS'!$E15,,MATCH(O15,'Alíquotas ICMS'!$E15:$L15,0)-2),O$4)-O$4)*N15)/(EOMONTH(O$4,0)-O$4),4) -> 0.18
B47: =B16 -> MS | D47: =ROUND(((EOMONTH(D$4,0)-MAX(OFFSET('Alíquotas ICMS'!$E16,,MATCH(D16,'Alíquotas ICMS'!$E16:$L16,0)-2),D$4))*D16+(MAX(OFFSET('Alíquotas ICMS'!$E16,,MATCH(D16,'Alíquotas ICMS'!$E16:$L16,0)-2),D$4)-D$4)*C16)/(EOMONTH(D$4,0)-D$4),4) -> 0.29 | E47: =ROUND(((EOMONTH(E$4,0)-MAX(OFFSET('Alíquotas ICMS'!$E16,,MATCH(E16,'Alíquotas ICMS'!$E16:$L16,0)-2),E$4))*E16+(MAX(OFFSET('Alíquotas ICMS'!$E16,,MATCH(E16,'Alíquotas ICMS'!$E16:$L16,0)-2),E$4)-E$4)*D16)/(EOMONTH(E$4,0)-E$4),4) -> 0.29 | F47: =ROUND(((EOMONTH(F$4,0)-MAX(OFFSET('Alíquotas ICMS'!$E16,,MATCH(F16,'Alíquotas ICMS'!$E16:$L16,0)-2),F$4))*F16+(MAX(OFFSET('Alíquotas ICMS'!$E16,,MATCH(F16,'Alíquotas ICMS'!$E16:$L16,0)-2),F$4)-F$4)*E16)/(EOMONTH(F$4,0)-F$4),4) -> 0.29 | G47: =ROUND(((EOMONTH(G$4,0)-MAX(OFFSET('Alíquotas ICMS'!$E16,,MATCH(G16,'Alíquotas ICMS'!$E16:$L16,0)-2),G$4))*G16+(MAX(OFFSET('Alíquotas ICMS'!$E16,,MATCH(G16,'Alíquotas ICMS'!$E16:$L16,0)-2),G$4)-G$4)*F16)/(EOMONTH(G$4,0)-G$4),4) -> 0.29 | H47: =ROUND(((EOMONTH(H$4,0)-MAX(OFFSET('Alíquotas ICMS'!$E16,,MATCH(H16,'Alíquotas ICMS'!$E16:$L16,0)-2),H$4))*H16+(MAX(OFFSET('Alíquotas ICMS'!$E16,,MATCH(H16,'Alíquotas ICMS'!$E16:$L16,0)-2),H$4)-H$4)*G16)/(EOMONTH(H$4,0)-H$4),4) -> 0.29 | I47: =ROUND(((EOMONTH(I$4,0)-MAX(OFFSET('Alíquotas ICMS'!$E16,,MATCH(I16,'Alíquotas ICMS'!$E16:$L16,0)-2),I$4))*I16+(MAX(OFFSET('Alíquotas ICMS'!$E16,,MATCH(I16,'Alíquotas ICMS'!$E16:$L16,0)-2),I$4)-I$4)*H16)/(EOMONTH(I$4,0)-I$4),4) -> 0.29 | J47: =ROUND(((EOMONTH(J$4,0)-MAX(OFFSET('Alíquotas ICMS'!$E16,,MATCH(J16,'Alíquotas ICMS'!$E16:$L16,0)-2),J$4))*J16+(MAX(OFFSET('Alíquotas ICMS'!$E16,,MATCH(J16,'Alíquotas ICMS'!$E16:$L16,0)-2),J$4)-J$4)*I16)/(EOMONTH(J$4,0)-J$4),4) -> 0.19 | K47: =ROUND(((EOMONTH(K$4,0)-MAX(OFFSET('Alíquotas ICMS'!$E16,,MATCH(K16,'Alíquotas ICMS'!$E16:$L16,0)-2),K$4))*K16+(MAX(OFFSET('Alíquotas ICMS'!$E16,,MATCH(K16,'Alíquotas ICMS'!$E16:$L16,0)-2),K$4)-K$4)*J16)/(EOMONTH(K$4,0)-K$4),4) -> 0.19 | ... O47: =ROUND(((EOMONTH(O$4,0)-MAX(OFFSET('Alíquotas ICMS'!$E16,,MATCH(O16,'Alíquotas ICMS'!$E16:$L16,0)-2),O$4))*O16+(MAX(OFFSET('Alíquotas ICMS'!$E16,,MATCH(O16,'Alíquotas ICMS'!$E16:$L16,0)-2),O$4)-O$4)*N16)/(EOMONTH(O$4,0)-O$4),4) -> 0.19
... B62: =B31 -> TO | D62: =ROUND(((EOMONTH(D$4,0)-MAX(OFFSET('Alíquotas ICMS'!$E31,,MATCH(D31,'Alíquotas ICMS'!$E31:$L31,0)-2),D$4))*D31+(MAX(OFFSET('Alíquotas ICMS'!$E31,,MATCH(D31,'Alíquotas ICMS'!$E31:$L31,0)-2),D$4)-D$4)*C31)/(EOMONTH(D$4,0)-D$4),4) -> 0.29 | E62: =ROUND(((EOMONTH(E$4,0)-MAX(OFFSET('Alíquotas ICMS'!$E31,,MATCH(E31,'Alíquotas ICMS'!$E31:$L31,0)-2),E$4))*E31+(MAX(OFFSET('Alíquotas ICMS'!$E31,,MATCH(E31,'Alíquotas ICMS'!$E31:$L31,0)-2),E$4)-E$4)*D31)/(EOMONTH(E$4,0)-E$4),4) -> 0.29 | F62: =ROUND(((EOMONTH(F$4,0)-MAX(OFFSET('Alíquotas ICMS'!$E31,,MATCH(F31,'Alíquotas ICMS'!$E31:$L31,0)-2),F$4))*F31+(MAX(OFFSET('Alíquotas ICMS'!$E31,,MATCH(F31,'Alíquotas ICMS'!$E31:$L31,0)-2),F$4)-F$4)*E31)/(EOMONTH(F$4,0)-F$4),4) -> 0.29 | G62: =ROUND(((EOMONTH(G$4,0)-MAX(OFFSET('Alíquotas ICMS'!$E31,,MATCH(G31,'Alíquotas ICMS'!$E31:$L31,0)-2),G$4))*G31+(MAX(OFFSET('Alíquotas ICMS'!$E31,,MATCH(G31,'Alíquotas ICMS'!$E31:$L31,0)-2),G$4)-G$4)*F31)/(EOMONTH(G$4,0)-G$4),4) -> 0.29 | H62: =ROUND(((EOMONTH(H$4,0)-MAX(OFFSET('Alíquotas ICMS'!$E31,,MATCH(H31,'Alíquotas ICMS'!$E31:$L31,0)-2),H$4))*H31+(MAX(OFFSET('Alíquotas ICMS'!$E31,,MATCH(H31,'Alíquotas ICMS'!$E31:$L31,0)-2),H$4)-H$4)*G31)/(EOMONTH(H$4,0)-H$4),4) -> 0.29 | I62: =ROUND(((EOMONTH(I$4,0)-MAX(OFFSET('Alíquotas ICMS'!$E31,,MATCH(I31,'Alíquotas ICMS'!$E31:$L31,0)-2),I$4))*I31+(MAX(OFFSET('Alíquotas ICMS'!$E31,,MATCH(I31,'Alíquotas ICMS'!$E31:$L31,0)-2),I$4)-I$4)*H31)/(EOMONTH(I$4,0)-I$4),4) -> 0.29 | J62: =ROUND(((EOMONTH(J$4,0)-MAX(OFFSET('Alíquotas ICMS'!$E31,,MATCH(J31,'Alíquotas ICMS'!$E31:$L31,0)-2),J$4))*J31+(MAX(OFFSET('Alíquotas ICMS'!$E31,,MATCH(J31,'Alíquotas ICMS'!$E31:$L31,0)-2),J$4)-J$4)*I31)/(EOMONTH(J$4,0)-J$4),4) -> 0.29 | K62: =ROUND(((EOMONTH(K$4,0)-MAX(OFFSET('Alíquotas ICMS'!$E31,,MATCH(K31,'Alíquotas ICMS'!$E31:$L31,0)-2),K$4))*K31+(MAX(OFFSET('Alíquotas ICMS'!$E31,,MATCH(K31,'Alíquotas ICMS'!$E31:$L31,0)-2),K$4)-K$4)*J31)/(EOMONTH(K$4,0)-K$4),4) -> 0.1837 | ... O62: =ROUND(((EOMONTH(O$4,0)-MAX(OFFSET('Alíquotas ICMS'!$E31,,MATCH(O31,'Alíquotas ICMS'!$E31:$L31,0)-2),O$4))*O31+(MAX(OFFSET('Alíquotas ICMS'!$E31,,MATCH(O31,'Alíquotas ICMS'!$E31:$L31,0)-2),O$4)-O$4)*N31)/(EOMONTH(O$4,0)-O$4),4) -> 0.18
B63: NT | D63: 0 | E63: 0 | F63: 0 | G63: 0 | H63: 0 | I63: 0 | J63: 0 | K63: 0 | L63: 0 | M63: 0 | N63: 0 | O63: 0

Sheet Alíquotas ICMS
B2: Alíquotas estaduais ICMS - telecomunicações (*valores totais já com eventuais adicionais dos Fundos estaduais de combate a pobreza - FECP)
B4: UF | C4: Normativo Geral (apenas alíquota base, sem FECP) | D4: Normativo de vigência da LC 194/2022 | E4: Vigência a partir de: | F4: Alíquota máxima | G4: Vigência a partir de:2 | H4: Alíquota máxima3 | I4: Vigência a partir de:4 | J4: Alíquota máxima5 | K4: Vigência a partir de:6 | L4: Alíquota máxima7 | O4: Alíquota
B5: AC | C5: Lei Complementar 55/97 art. 18, III, Item 7 - DECRETO Nº 008, DE 26 DE JANEIRO DE 1998 | D5: DECRETO Nº 11.084, DE 7 DE JULHO DE 2022 | E5: 41639 | F5: 0.25 | G5: 44749 | H5: 0.17 | I5: 45017 | J5: 0.19 | K5: - | O5: 0
B6: AL | C6: Lei nº 5.900/96, art. 17, inciso I, d | D6: DECRETO Nº 83.840, DE 01 DE JULHO DE 2022 | E6: 42380 | F6: 0.3 | G6: 44749 | H6: 0.19 | I6: 45017 | J6: 0.21 | K6: - | L6: - | O6: 0.1
B7: AM | C7: Lei Complementar 19/1997, art. 12, inciso I, e, f | D7: DECRETO N° 45.973, DE 05 DE JULHO DE 2022 | E7: 41365 | F7: 0.3 | G7: 44743 | H7: 0.18 | I7: 45014 | J7: 0.2 | K7: - | L7: - | O7: 0.25
B8: AP | C8: DECRETO Nº 2269 DE 24 DE JULHO DE 1998 - Anexo I RICMS/AP - art. 25, inciso III, alínea a | D8: ADI 7.126 DE 14 de setembro de 2022 | E8: 42459 | F8: 0.29 | G8: 45383 | H8: 0.18 | I8: - | J8: - | K8: - | L8: - | O8: 0.27
B9: BA | C9: Lei n° 7.014/1996 - art. 15, inciso V | D9: Decreto Nº 21494 DE 04/07/2022 | E9: 41271 | F9: 0.28 | G9: 44735 | H9: 0.18 | I9: 45007 | J9: 0.19 | K9: 45329 | L9: 0.205 | O9: 0.28
B10: CE | C10: RICMS/CE - art. 45, inciso II, a | D10: Lei nº 18.154/22 e LC nº 287/22 | E10: 42430 | F10: 0.3 | G10: 44754 | H10: 0.18 | I10: 45292 | J10: 0.2 | K10: - | L10: - | O10: 0.29
B11: DF | C11: Lei nº 1.254/1996 - art. 18, inciso II, f | D11: Decreto nº 43.521/22 | E11: 44562 | F11: 0.28 | G11: 44735 | H11: 0.18 | I11: - | J11: - | K11: - | L11: - | O11: 0.3
B12: ES | C12: RICMS/ES, art. 71, inciso IV | D12: Decreto nº 5164-R/22 | E12: 37257 | F12: 0.25 | G12: 44743 | H12: 0.17 | I12: - | J12: - | K12: - | L12: - | O12: 0.32
B13: GO | C13: RCTE/GO, art. 20, §1º, V | D13: Nota GSE s/nº/2022 - DOE GO - Suplemento de 27.06.2022 | E13: 38808 | F13: 0.29 | G13: 44735 | H13: 0.17 | I13: - | J13: - | K13: - | L13: - | O13: 0.35
B14: MA | C14: Lei nº 7.799/2002, art. 23, inciso III, alínea "h" | D14: Lei nº 11.792/2022 | E14: 42809 | F14: 0.29 | G14: 44755 | H14: 0.18 | I14: 45017 | J14: 0.2 | K14: - | L14: -
B15: MG | C15: Lei n° 6.763/1975, Item 10, tabela F | D15: Decreto nº 48.456/22 | E15: 43831 | F15: 0.27 | G15: 44735 | H15: 0.18 | I15: - | J15: - | K15: - | L15: -
B16: MS | C16: Lei nº 1.810/1997, art. 41, inciso IV | D16: Decreto nº 15.990/22 | E16: 37622 | F16: 0.29 | G16: 44743 | H16: 0.19 | I16: - | J16: - | K16: - | L16: -
B17: MT | C17: RICMS/MT, art. 95, inciso I, alínea "g" | D17: Mudança em Jan/22 | E17: 44562 | F17: 0.19 | G17: 44562 | H17: 0.19 | I17: - | J17: - | K17: - | L17: -
B18: PA | C18: Lei n° 5.530/1989, art. 12, inciso I | D18: Decreto nº 2.476/22 | E18: 40114 | F18: 0.3 | G18: 44746 | H18: 0.17 | I18: 45001 | J18: 0.19 | K18: - | L18: -
B19: PB | C19: RICMS/PB, art. 13, inciso VI | D19: Decreto nº 42.656/22 | E19: 38353 | F19: 0.3 | G19: 44735 | H19: 0.2 | I19: - | J19: - | K19: - | L19: -
B20: PE | C20: Lei nº 15.730/2016, art. 15, inciso I, alínea "a" | D20: Lei nº 17.898/22 | E20: 43556 | F20: 0.3 | G20: 44757 | H20: 0.18 | I20: - | J20: - | K20: - | L20: -
B21: PI | C21: Lei 7.054/2017, art. 20, IV c/c Comunicado SEFAZ n° 06/2017 | D21: Lei nº 7.846/22 | E21: 43135 | F21: 0.3 | G21: 44754 | H21: 0.18 | I21: 44993 | J21: 0.21 | K21: - | L21: -
B22: PR | C22: Lei n° 16.016/2008, art. 1º, inciso I | D22: Boletim Informativo nº 005/22 | E22: 39904 | F22: 0.29 | G22: 44735 | H22: 0.18 | I22: 44998 | J22: 0.19 | K22: - | L22: -
B23: RJ | C23: Lei 7.508/2016, art. 1 | D23: Decreto nº 48.145/22 | E23: 42824 | F23: 0.32 | G23: 44743 | H23: 0.22 | I23: - | J23: - | K23: - | L23: -
B24: RN | C24: Lei nº 6.968/1996, art. 27, inciso I, alínea “e” | D24: Decreto nº 31.656/22 | E24: 42397 | F24: 0.3 | G24: 44735 | H24: 0.18 | I24: 45017 | J24: 0.2 | K24: - | L24: -
B25: RO | C25: Lei Estadual n° 688/1996, art. 27, "e" | D25: Lei 5.364/2022 | E25: 36526 | F25: 0.35 | G25: 44735 | H25: 0.175 | I25: 45017 | J25: 0.2 | K25: - | L25: -
B26: RR | C26: Decreto 4335-E/2001, art. 46, iniciso III, a | D26: Decreto nº 32.806-E/22 | E26: 37165 | F26: 0.25 | G26: 44746 | H26: 0.17 | I26: 45015 | J26: 0.2 | K26: - | L26: -
B27: RS | C27: RICMS/RS, art. 28, inciso I do Livro I | D27: Decreto nº 56.573/22 e Decreto nº 56.604/22 | E27: 44562 | F27: 0.25 | G27: 44735 | H27: 0.17 | I27: - | J27: - | K27: - | L27: -
B28: SC | C28: RICMS/SC, art. 26, inciso II, a | D28: MP 255/2022 | E28: 42370 | F28: 0.25 | G28: 44743 | H28: 0.17 | I28: - | J28: - | K28: - | L28: -
B29: SE | C29: Decreto n° 30.113/2015, art. 1º | D29: Decreto nº 112/2022 | E29: 42370 | F29: 0.3 | G29: 44747 | H29: 0.18 | I29: 45005 | J29: 0.22 | K29: - | L29: -
B30: SP | C30: RICMS/SP, art. 55, inciso I | D30: Informativo SPF D.O.E. | E30: 33599 | F30: 0.25 | G30: 44735 | H30: 0.18 | I30: - | J30: - | K30: - | L30: -
B31: TO | C31: Lei nº 1.287/2001, art. 27, inciso I, a | D31: MP nº 21/22 | E31: 37257 | F31: 0.29 | G31: 44775 | H31: 0.18 | I31: 45017 | J31: 0.2 | K31: - | L31: -
